Workbook

Sheet data
A1: order_id | B1: order_date | C1: ship_date | D1: customer_id | E1: customer_name | F1: segment | G1: region | H1: state | I1: city | J1: category | K1: sub_category | L1: product_name | M1: ship_mode | N1: quantity | O1: unit_price | P1: discount | Q1: sales | R1: cost | S1: profit | T1: payment_status | U1: order_status | V1: Profit Margin | W1: Order moth | X1: Order Year | Y1: Shipping_Delay_Days | Z1: Cleaned Discount | AA1: Calculated Sales | AB1: Calculated Profit | AC1: Data Quality Flag
A2: ORD-2024-10001 | B2: 45494 | C2: 45500 | D2: CUST-4655 | E2: =PROPER(TRIM([1]raw_orders!E2)) -> Karan Malhotra | F2: =PROPER(TRIM([1]raw_orders!F2)) -> Consumer | G2: =IF('[1]Cleaned Text Field'!G2="","Unknown",'[1]Cleaned Text Field'!G2) -> North | H2: =PROPER(TRIM([1]raw_orders!H2)) -> Rajasthan | I2: =PROPER(TRIM([1]raw_orders!I2)) -> Jaipur | J2: =PROPER(TRIM([1]raw_orders!J2)) -> Office Supplies | K2: =PROPER(TRIM([1]raw_orders!K2)) -> Paper | L2: Pro Paper 122 | M2: =IF('[1]Cleaned Text Field'!M2="","Unknown",'[1]Cleaned Text Field'!M2) -> Second Class | N2: =IF('[1]Cleaned Text Field'!N2="",0,'[1]Cleaned Text Field'!N2) -> 8 | O2: 2976.45 | P2: =IF('[1]Cleaned Text Field'!P2="",0,'[1]Cleaned Text Field'!P2) -> 0.2 | Q2: 19049.28 | R2: 15841.89 | S2: 3207.39 | T2: =PROPER(TRIM([1]raw_orders!T2)) -> Paid | U2: =PROPER(TRIM([1]raw_orders!U2)) -> Completed | V2: =IF(Q2=0,0,S2/Q2) -> 0.16837329 | W2: =TEXT(B2,"mmmm") -> July | X2: =YEAR(B2) -> 2024 | Y2: =C2-B2 -> 6 | Z2: =P2 -> 0.2 | AA2: =N2*O2*(1-P2) -> 19049.28 | AB2: =Q2-R2 -> 3207.39 | AC2: =IF(OR(B2="",C2="",AA2<=0),"Invalid",IF(Y2<0,"Warning",IF(Z2>100%,"Warning","Clean"))) -> Clean
A3: ORD-2024-10002 | B3: 45535 | C3: 45540 | D3: CUST-2054 | E3: =PROPER(TRIM([1]raw_orders!E3)) -> Mira Das | F3: =PROPER(TRIM([1]raw_orders!F3)) -> Small Business | G3: =IF('[1]Cleaned Text Field'!G3="","Unknown",'[1]Cleaned Text Field'!G3) -> East | H3: =PROPER(TRIM([1]raw_orders!H3)) -> Odisha | I3: =PROPER(TRIM([1]raw_orders!I3)) -> Bhubaneswar | J3: =PROPER(TRIM([1]raw_orders!J3)) -> Furniture | K3: =PROPER(TRIM([1]raw_orders!K3)) -> Tables | L3: Pro Tables 258 | M3: =IF('[1]Cleaned Text Field'!M3="","Unknown",'[1]Cleaned Text Field'!M3) -> Same Day | N3: =IF('[1]Cleaned Text Field'!N3="",0,'[1]Cleaned Text Field'!N3) -> 3 | O3: 2437.5 | P3: =IF('[1]Cleaned Text Field'!P3="",0,'[1]Cleaned Text Field'!P3) -> 0 | Q3: 7312.5 | R3: 4904.73 | S3: 2407.77 | T3: =PROPER(TRIM([1]raw_orders!T3)) -> Paid | U3: =PROPER(TRIM([1]raw_orders!U3)) -> Completed | V3: =IF(Q3=0,0,S3/Q3) -> 0.32926769 | W3: =TEXT(B3,"mmmm") -> August | X3: =YEAR(B3) -> 2024 | Y3: =C3-B3 -> 5 | Z3: =P3 -> 0 | AA3: =N3*O3*(1-P3) -> 7312.5 | AB3: =Q3-R3 -> 2407.77 | AC3: =IF(OR(B3="",C3="",AA3<=0),"Invalid",IF(Y3<0,"Warning",IF(Z3>100%,"Warning","Clean"))) -> Clean
A4: ORD-2024-10003 | B4: 45451 | C4: 45458 | D4: CUST-6843 | E4: =PROPER(TRIM([1]raw_orders!E4)) -> Isha Nair | F4: =PROPER(TRIM([1]raw_orders!F4)) -> Consumer | G4: =IF('[1]Cleaned Text Field'!G4="","Unknown",'[1]Cleaned Text Field'!G4) -> East | H4: =PROPER(TRIM([1]raw_orders!H4)) -> Odisha | I4: =PROPER(TRIM([1]raw_orders!I4)) -> Bhubaneswar | J4: =PROPER(TRIM([1]raw_orders!J4)) -> Office Supplies | K4: =PROPER(TRIM([1]raw_orders!K4)) -> Art | L4: Elite Art 525 | M4: =IF('[1]Cleaned Text Field'!M4="","Unknown",'[1]Cleaned Text Field'!M4) -> First Class | N4: =IF('[1]Cleaned Text Field'!N4="",0,'[1]Cleaned Text Field'!N4) -> 4 | O4: 1065.43 | P4: =IF('[1]Cleaned Text Field'!P4="",0,'[1]Cleaned Text Field'!P4) -> 0.55 | Q4: 4261.72 | R4: 2465.69 | S4: 1796.03 | T4: =PROPER(TRIM([1]raw_orders!T4)) -> Paid | U4: =PROPER(TRIM([1]raw_orders!U4)) -> Completed | V4: =IF(Q4=0,0,S4/Q4) -> 0.42143313 | W4: =TEXT(B4,"mmmm") -> June | X4: =YEAR(B4) -> 2024 | Y4: =C4-B4 -> 7 | Z4: =P4 -> 0.55 | AA4: =N4*O4*(1-P4) -> 1917.774 | AB4: =Q4-R4 -> 1796.03 | AC4: =IF(OR(B4="",C4="",AA4<=0),"Invalid",IF(Y4<0,"Warning",IF(Z4>100%,"Warning","Clean"))) -> Clean
A5: ORD-2024-10004 | B5: 45624 | C5: 45625 | D5: CUST-3722 | E5: =PROPER(TRIM([1]raw_orders!E5)) -> Arjun Bose | F5: =PROPER(TRIM([1]raw_orders!F5)) -> Small Business | G5: =IF('[1]Cleaned Text Field'!G5="","Unknown",'[1]Cleaned Text Field'!G5) -> South | H5: =PROPER(TRIM([1]raw_orders!H5)) -> Telangana | I5: =PROPER(TRIM([1]raw_orders!I5)) -> Hyderabad | J5: =PROPER(TRIM([1]raw_orders!J5)) -> Furniture | K5: =PROPER(TRIM([1]raw_orders!K5)) -> Furnishings | L5: Smart Furnishings 294 | M5: =IF('[1]Cleaned Text Field'!M5="","Unknown",'[1]Cleaned Text Field'!M5) -> Standard Class | N5: =IF('[1]Cleaned Text Field'!N5="",0,'[1]Cleaned Text Field'!N5) -> 6 | O5: 1848.43 | P5: =IF('[1]Cleaned Text Field'!P5="",0,'[1]Cleaned Text Field'!P5) -> 0.25 | Q5: 8317.93 | R5: 6796.77 | S5: 1521.16 | T5: =PROPER(TRIM([1]raw_orders!T5)) -> Paid | U5: =PROPER(TRIM([1]raw_orders!U5)) -> Completed | V5: =IF(Q5=0,0,S5/Q5) -> 0.18287723 | W5: =TEXT(B5,"mmmm") -> November | X5: =YEAR(B5) -> 2024 | Y5: =C5-B5 -> 1 | Z5: =P5 -> 0.25 | AA5: =N5*O5*(1-P5) -> 8317.935 | AB5: =Q5-R5 -> 1521.16 | AC5: =IF(OR(B5="",C5="",AA5<=0),"Invalid",IF(Y5<0,"Warning",IF(Z5>100%,"Warning","Clean"))) -> Clean
A6: ORD-2025-10005 | B6: 45898 | C6: 45901 | D6: CUST-8130 | E6: =PROPER(TRIM([1]raw_orders!E6)) -> Ananya Rao | F6: =PROPER(TRIM([1]raw_orders!F6)) -> Small Business | G6: =IF('[1]Cleaned Text Field'!G6="","Unknown",'[1]Cleaned Text Field'!G6) -> West | H6: =PROPER(TRIM([1]raw_orders!H6)) -> Maharashtra | I6: =PROPER(TRIM([1]raw_orders!I6)) -> Mumbai | J6: =PROPER(TRIM([1]raw_orders!J6)) -> Furniture | K6: =PROPER(TRIM([1]raw_orders!K6)) -> Chairs | L6: Elite Chairs 543 | M6: =IF('[1]Cleaned Text Field'!M6="","Unknown",'[1]Cleaned Text Field'!M6) -> First Class | N6: =IF('[1]Cleaned Text Field'!N6="",0,'[1]Cleaned Text Field'!N6) -> 7 | O6: 2973.76 | P6: =IF('[1]Cleaned Text Field'!P6="",0,'[1]Cleaned Text Field'!P6) -> 0 | Q6: 20816.32 | R6: 17705.37 | S6: 3110.95 | T6: =PROPER(TRIM([1]raw_orders!T6)) -> Paid | U6: =PROPER(TRIM([1]raw_orders!U6)) -> Cancelled | V6: =IF(Q6=0,0,S6/Q6) -> 0.14944764 | W6: =TEXT(B6,"mmmm") -> August | X6: =YEAR(B6) -> 2025 | Y6: =C6-B6 -> 3 | Z6: =P6 -> 0 | AA6: =N6*O6*(1-P6) -> 20816.32 | AB6: =Q6-R6 -> 3110.95 | AC6: =IF(OR(B6="",C6="",AA6<=0),"Invalid",IF(Y6<0,"Warning",IF(Z6>100%,"Warning","Clean"))) -> Clean
A7: ORD-2024-10006 | B7: 45436 | C7: 45440 | D7: CUST-6056 | E7: =PROPER(TRIM([1]raw_orders!E7)) -> Vikram Iyer | F7: =PROPER(TRIM([1]raw_orders!F7)) -> Small Business | G7: =IF('[1]Cleaned Text Field'!G7="","Unknown",'[1]Cleaned Text Field'!G7) -> West | H7: =PROPER(TRIM([1]raw_orders!H7)) -> Madhya Pradesh | I7: =PROPER(TRIM([1]raw_orders!I7)) -> Indore | J7: =PROPER(TRIM([1]raw_orders!J7)) -> Technology | K7: =PROPER(TRIM([1]raw_orders!K7)) -> Accessories | L7: Pro Accessories 821 | M7: =IF('[1]Cleaned Text Field'!M7="","Unknown",'[1]Cleaned Text Field'!M7) -> Same Day | N7: =IF('[1]Cleaned Text Field'!N7="",0,'[1]Cleaned Text Field'!N7) -> 3 | O7: 1053.11 | P7: =IF('[1]Cleaned Text Field'!P7="",0,'[1]Cleaned Text Field'!P7) -> 0.2 | Q7: 2527.46 | R7: 1533.58 | S7: 993.88 | T7: =PROPER(TRIM([1]raw_orders!T7)) -> Paid | U7: =PROPER(TRIM([1]raw_orders!U7)) -> Completed | V7: =IF(Q7=0,0,S7/Q7) -> 0.39323273 | W7: =TEXT(B7,"mmmm") -> May | X7: =YEAR(B7) -> 2024 | Y7: =C7-B7 -> 4 | Z7: =P7 -> 0.2 | AA7: =N7*O7*(1-P7) -> 2527.464 | AB7: =Q7-R7 -> 993.88 | AC7: =IF(OR(B7="",C7="",AA7<=0),"Invalid",IF(Y7<0,"Warning",IF(Z7>100%,"Warning","Clean"))) -> Clean
A8: ORD-2025-10007 | B8: 45757 | C8: 45763 | D8: CUST-3656 | E8: =PROPER(TRIM([1]raw_orders!E8)) -> Neha Gupta | F8: =PROPER(TRIM([1]raw_orders!F8)) -> Consumer | G8: =IF('[1]Cleaned Text Field'!G8="","Unknown",'[1]Cleaned Text Field'!G8) -> East | H8: =PROPER(TRIM([1]raw_orders!H8)) -> Odisha | I8: =PROPER(TRIM([1]raw_orders!I8)) -> Bhubaneswar | J8: =PROPER(TRIM([1]raw_orders!J8)) -> Technology | K8: =PROPER(TRIM([1]raw_orders!K8)) -> Copiers | L8: Eco Copiers 790 | M8: =IF('[1]Cleaned Text Field'!M8="","Unknown",'[1]Cleaned Text Field'!M8) -> Standard Class | N8: =IF('[1]Cleaned Text Field'!N8="",0,'[1]Cleaned Text Field'!N8) -> 4 | O8: 1719.87 | P8: =IF('[1]Cleaned Text Field'!P8="",0,'[1]Cleaned Text Field'!P8) -> 0.15 | Q8: 5847.56 | R8: 4727.25 | S8: 1120.31 | T8: =PROPER(TRIM([1]raw_orders!T8)) -> Paid | U8: =PROPER(TRIM([1]raw_orders!U8)) -> Completed | V8: =IF(Q8=0,0,S8/Q8) -> 0.19158589 | W8: =TEXT(B8,"mmmm") -> April | X8: =YEAR(B8) -> 2025 | Y8: =C8-B8 -> 6 | Z8: =P8 -> 0.15 | AA8: =N8*O8*(1-P8) -> 5847.558 | AB8: =Q8-R8 -> 1120.31 | AC8: =IF(OR(B8="",C8="",AA8<=0),"Invalid",IF(Y8<0,"Warning",IF(Z8>100%,"Warning","Clean"))) -> Clean
A9: ORD-2025-10008 | B9: 45711 | C9: 45714 | D9: CUST-4683 | E9: =PROPER(TRIM([1]raw_orders!E9)) -> Isha Nair | F9: =PROPER(TRIM([1]raw_orders!F9)) -> Small Business | G9: =IF('[1]Cleaned Text Field'!G9="","Unknown",'[1]Cleaned Text Field'!G9) -> South | H9: =PROPER(TRIM([1]raw_orders!H9)) -> Andhra Pradesh | I9: =PROPER(TRIM([1]raw_orders!I9)) -> Vijayawada | J9: =PROPER(TRIM([1]raw_orders!J9)) -> Office Supplies | K9: =PROPER(TRIM([1]raw_orders!K9)) -> Art | L9: Eco Art 848 | M9: =IF('[1]Cleaned Text Field'!M9="","Unknown",'[1]Cleaned Text Field'!M9) -> First Class | N9: =IF('[1]Cleaned Text Field'!N9="",0,'[1]Cleaned Text Field'!N9) -> 1 | O9: 2980.71 | P9: =IF('[1]Cleaned Text Field'!P9="",0,'[1]Cleaned Text Field'!P9) -> 0 | Q9: 2980.71 | R9: 2357.22 | S9: 623.49 | T9: =PROPER(TRIM([1]raw_orders!T9)) -> Paid | U9: =PROPER(TRIM([1]raw_orders!U9)) -> Completed | V9: =IF(Q9=0,0,S9/Q9) -> 0.209175 | W9: =TEXT(B9,"mmmm") -> February | X9: =YEAR(B9) -> 2025 | Y9: =C9-B9 -> 3 | Z9: =P9 -> 0 | AA9: =N9*O9*(1-P9) -> 2980.71 | AB9: =Q9-R9 -> 623.49 | AC9: =IF(OR(B9="",C9="",AA9<=0),"Invalid",IF(Y9<0,"Warning",IF(Z9>100%,"Warning","Clean"))) -> Clean
A10: ORD-2024-10009 | B10: 45601 | C10: 45606 | D10: CUST-2598 | E10: =PROPER(TRIM([1]raw_orders!E10)) -> Aditi Sen | F10: =PROPER(TRIM([1]raw_orders!F10)) -> Corporate | G10: =IF('[1]Cleaned Text Field'!G10="","Unknown",'[1]Cleaned Text Field'!G10) -> South | H10: =PROPER(TRIM([1]raw_orders!H10)) -> Telangana | I10: =PROPER(TRIM([1]raw_orders!I10)) -> Hyderabad | J10: =PROPER(TRIM([1]raw_orders!J10)) -> Office Supplies | K10: =PROPER(TRIM([1]raw_orders!K10)) -> Labels | L10: Classic Labels 815 | M10: =IF('[1]Cleaned Text Field'!M10="","Unknown",'[1]Cleaned Text Field'!M10) -> First Class | N10: =IF('[1]Cleaned Text Field'!N10="",0,'[1]Cleaned Text Field'!N10) -> 8 | O10: 3134.2 | P10: =IF('[1]Cleaned Text Field'!P10="",0,'[1]Cleaned Text Field'!P10) -> 0 | Q10: 25073.6 | R10: 17347.23 | S10: 7726.37 | T10: =PROPER(TRIM([1]raw_orders!T10)) -> Paid | U10: =PROPER(TRIM([1]raw_orders!U10)) -> Completed | V10: =IF(Q10=0,0,S10/Q10) -> 0.30814761 | W10: =TEXT(B10,"mmmm") -> November | X10: =YEAR(B10) -> 2024 | Y10: =C10-B10 -> 5 | Z10: =P10 -> 0 | AA10: =N10*O10*(1-P10) -> 25073.6 | AB10: =Q10-R10 -> 7726.37 | AC10: =IF(OR(B10="",C10="",AA10<=0),"Invalid",IF(Y10<0,"Warning",IF(Z10>100%,"Warning","Clean"))) -> Clean
A11: ORD-2025-10010 | B11: 45847 | C11: 45912 | D11: CUST-2483 | E11: =PROPER(TRIM([1]raw_orders!E11)) -> Mira Das | F11: =PROPER(TRIM([1]raw_orders!F11)) -> Home Office | G11: =IF('[1]Cleaned Text Field'!G11="","Unknown",'[1]Cleaned Text Field'!G11) -> South | H11: =PROPER(TRIM([1]raw_orders!H11)) -> Telangana | I11: =PROPER(TRIM([1]raw_orders!I11)) -> Hyderabad | J11: =PROPER(TRIM([1]raw_orders!J11)) -> Office Supplies | K11: =PROPER(TRIM([1]raw_orders!K11)) -> Paper | L11: Pro Paper 622 | M11: =IF('[1]Cleaned Text Field'!M11="","Unknown",'[1]Cleaned Text Field'!M11) -> Second Class | N11: =IF('[1]Cleaned Text Field'!N11="",0,'[1]Cleaned Text Field'!N11) -> 9 | O11: 852.04 | P11: =IF('[1]Cleaned Text Field'!P11="",0,'[1]Cleaned Text Field'!P11) -> 0.2 | Q11: 6134.69 | R11: 3800.19 | S11: 2334.5 | T11: =PROPER(TRIM([1]raw_orders!T11)) -> Paid | U11: =PROPER(TRIM([1]raw_orders!U11)) -> Completed | V11: =IF(Q11=0,0,S11/Q11) -> 0.38054083 | W11: =TEXT(B11,"mmmm") -> July | X11: =YEAR(B11) -> 2025 | Y11: =C11-B11 -> 65 | Z11: =P11 -> 0.2 | AA11: =N11*O11*(1-P11) -> 6134.688 | AB11: =Q11-R11 -> 2334.5 | AC11: =IF(OR(B11="",C11="",AA11<=0),"Invalid",IF(Y11<0,"Warning",IF(Z11>100%,"Warning","Clean"))) -> Clean
A12: ORD-2025-10011 | B12: 45797 | C12: 45797 | D12: CUST-8092 | E12: =PROPER(TRIM([1]raw_orders!E12)) -> Ananya Rao | F12: =PROPER(TRIM([1]raw_orders!F12)) -> Corporate | G12: =IF('[1]Cleaned Text Field'!G12="","Unknown",'[1]Cleaned Text Field'!G12) -> East | H12: =PROPER(TRIM([1]raw_orders!H12)) -> West Bengal | I12: =PROPER(TRIM([1]raw_orders!I12)) -> Kolkata | J12: =PROPER(TRIM([1]raw_orders!J12)) -> Office Supplies | K12: =PROPER(TRIM([1]raw_orders!K12)) -> Labels | L12: Prime Labels 644 | M12: =IF('[1]Cleaned Text Field'!M12="","Unknown",'[1]Cleaned Text Field'!M12) -> Second Class | N12: =IF('[1]Cleaned Text Field'!N12="",0,'[1]Cleaned Text Field'!N12) -> 3 | O12: 3534.83 | P12: =IF('[1]Cleaned Text Field'!P12="",0,'[1]Cleaned Text Field'!P12) -> 0.05 | Q12: 10074.27 | R12: 6048.27 | S12: 4026 | T12: =PROPER(TRIM([1]raw_orders!T12)) -> Refunded | U12: =PROPER(TRIM([1]raw_orders!U12)) -> Returned | V12: =IF(Q12=0,0,S12/Q12) -> 0.39963193 | W12: =TEXT(B12,"mmmm") -> May | X12: =YEAR(B12) -> 2025 | Y12: =C12-B12 -> 0 | Z12: =P12 -> 0.05 | AA12: =N12*O12*(1-P12) -> 10074.265 | AB12: =Q12-R12 -> 4026 | AC12: =IF(OR(B12="",C12="",AA12<=0),"Invalid",IF(Y12<0,"Warning",IF(Z12>100%,"Warning","Clean"))) -> Clean
A13: ORD-2024-10012 | B13: 45495 | C13: 45496 | D13: CUST-6528 | E13: =PROPER(TRIM([1]raw_orders!E13)) -> Vikram Iyer | F13: =PROPER(TRIM([1]raw_orders!F13)) -> Small Business | G13: =IF('[1]Cleaned Text Field'!G13="","Unknown",'[1]Cleaned Text Field'!G13) -> East | H13: =PROPER(TRIM([1]raw_orders!H13)) -> Odisha | I13: =PROPER(TRIM([1]raw_orders!I13)) -> Bhubaneswar | J13: =PROPER(TRIM([1]raw_orders!J13)) -> Technology | K13: =PROPER(TRIM([1]raw_orders!K13)) -> Accessories | L13: Smart Accessories 603 | M13: =IF('[1]Cleaned Text Field'!M13="","Unknown",'[1]Cleaned Text Field'!M13) -> Same Day | N13: =IF('[1]Cleaned Text Field'!N13="",0,'[1]Cleaned Text Field'!N13) -> 6 | O13: 2005.95 | P13: =IF('[1]Cleaned Text Field'!P13="",0,'[1]Cleaned Text Field'!P13) -> 0.2 | Q13: 9628.56 | R13: 8038.59 | S13: 1589.97 | T13: =PROPER(TRIM([1]raw_orders!T13)) -> Paid | U13: =PROPER(TRIM([1]raw_orders!U13)) -> Completed | V13: =IF(Q13=0,0,S13/Q13) -> 0.16513061 | W13: =TEXT(B13,"mmmm") -> July | X13: =YEAR(B13) -> 2024 | Y13: =C13-B13 -> 1 | Z13: =P13 -> 0.2 | AA13: =N13*O13*(1-P13) -> 9628.56 | AB13: =Q13-R13 -> 1589.97 | AC13: =IF(OR(B13="",C13="",AA13<=0),"Invalid",IF(Y13<0,"Warning",IF(Z13>100%,"Warning","Clean"))) -> Clean
... A118: ORD-2025-10117 | B118: 45703 | C118: 45707 | D118: CUST-3632 | E118: =PROPER(TRIM([1]raw_orders!E118)) -> Ananya Rao | F118: =PROPER(TRIM([1]raw_orders!F118)) -> Small Business | G118: =IF('[1]Cleaned Text Field'!G118="","Unknown",'[1]Cleaned Text Field'!G118) -> Unknown | H118: =PROPER(TRIM([1]raw_orders!H118)) -> Madhya Pradesh | I118: =PROPER(TRIM([1]raw_orders!I118)) -> Indore | J118: =PROPER(TRIM([1]raw_orders!J118)) -> Office Supplies | K118: =PROPER(TRIM([1]raw_orders!K118)) -> Binders | L118: Basic Binders 859 | M118: =IF('[1]Cleaned Text Field'!M118="","Unknown",'[1]Cleaned Text Field'!M118) -> First Class | N118: =IF('[1]Cleaned Text Field'!N118="",0,'[1]Cleaned Text Field'!N118) -> 9 | O118: 531.99 | P118: =IF('[1]Cleaned Text Field'!P118="",0,'[1]Cleaned Text Field'!P118) -> 0.25 | Q118: 3590.93 | R118: 3061.39 | S118: 529.54 | T118: =PROPER(TRIM([1]raw_orders!T118)) -> Failed | U118: =PROPER(TRIM([1]raw_orders!U118)) -> Cancelled | V118: =IF(Q118=0,0,S118/Q118) -> 0.14746598 | W118: =TEXT(B118,"mmmm") -> February | X118: =YEAR(B118) -> 2025 | Y118: =C118-B118 -> 4 | Z118: =P118 -> 0.25 | AA118: =N118*O118*(1-P118) -> 3590.9325 | AB118: =Q118-R118 -> 529.54 | AC118: =IF(OR(B118="",C118="",AA118<=0),"Invalid",IF(Y118<0,"Warning",IF(Z118>100%,"Warning","Clean"))) -> Clean
A119: ORD-2024-10118 | B119: 45337 | C119: 45339 | D119: CUST-9608 | E119: =PROPER(TRIM([1]raw_orders!E119)) -> Mira Das | F119: =PROPER(TRIM([1]raw_orders!F119)) -> Home Office | G119: =IF('[1]Cleaned Text Field'!G119="","Unknown",'[1]Cleaned Text Field'!G119) -> South | H119: =PROPER(TRIM([1]raw_orders!H119)) -> Tamil Nadu | I119: =PROPER(TRIM([1]raw_orders!I119)) -> Chennai | J119: =PROPER(TRIM([1]raw_orders!J119)) -> Technology | K119: =PROPER(TRIM([1]raw_orders!K119)) -> Machines | L119: Elite Machines 705 | M119: =IF('[1]Cleaned Text Field'!M119="","Unknown",'[1]Cleaned Text Field'!M119) -> Standard Class | N119: =IF('[1]Cleaned Text Field'!N119="",0,'[1]Cleaned Text Field'!N119) -> 9 | O119: 3324.55 | P119: =IF('[1]Cleaned Text Field'!P119="",0,'[1]Cleaned Text Field'!P119) -> 70% | Q119: 25432.81 | R119: 20370.16 | S119: 5062.65 | T119: =PROPER(TRIM([1]raw_orders!T119)) -> Paid | U119: =PROPER(TRIM([1]raw_orders!U119)) -> Completed | V119: =IF(Q119=0,0,S119/Q119) -> 0.1990598 | W119: =TEXT(B119,"mmmm") -> February | X119: =YEAR(B119) -> 2024 | Y119: =C119-B119 -> 2 | Z119: =VALUE(SUBSTITUTE(P119,"%",""))/100 -> 0.7 | AA119: =N119*O119*(1-P119) -> 8976.285 | AB119: =Q119-R119 -> 5062.65 | AC119: =IF(OR(B119="",C119="",AA119<=0),"Invalid",IF(Y119<0,"Warning",IF(Z119>100%,"Warning","Clean"))) -> Clean
A120: ORD-2024-10119 | B120: 45453 | C120: 45461 | D120: CUST-9135 | E120: =PROPER(TRIM([1]raw_orders!E120)) -> Vikram Iyer | F120: =PROPER(TRIM([1]raw_orders!F120)) -> Home Office | G120: =IF('[1]Cleaned Text Field'!G120="","Unknown",'[1]Cleaned Text Field'!G120) -> South | H120: =PROPER(TRIM([1]raw_orders!H120)) -> Andhra Pradesh | I120: =PROPER(TRIM([1]raw_orders!I120)) -> Vijayawada | J120: =PROPER(TRIM([1]raw_orders!J120)) -> Technology | K120: =PROPER(TRIM([1]raw_orders!K120)) -> Copiers | L120: Pro Copiers 208 | M120: =IF('[1]Cleaned Text Field'!M120="","Unknown",'[1]Cleaned Text Field'!M120) -> Same Day | N120: =IF('[1]Cleaned Text Field'!N120="",0,'[1]Cleaned Text Field'!N120) -> 5 | O120: 1580.27 | P120: =IF('[1]Cleaned Text Field'!P120="",0,'[1]Cleaned Text Field'!P120) -> 0.2 | Q120: 6321.08 | R120: 4407.22 | S120: 1913.86 | T120: =PROPER(TRIM([1]raw_orders!T120)) -> Paid | U120: =PROPER(TRIM([1]raw_orders!U120)) -> Completed | V120: =IF(Q120=0,0,S120/Q120) -> 0.30277421 | W120: =TEXT(B120,"mmmm") -> June | X120: =YEAR(B120) -> 2024 | Y120: =C120-B120 -> 8 | Z120: =P120 -> 0.2 | AA120: =N120*O120*(1-P120) -> 6321.08 | AB120: =Q120-R120 -> 1913.86 | AC120: =IF(OR(B120="",C120="",AA120<=0),"Invalid",IF(Y120<0,"Warning",IF(Z120>100%,"Warning","Clean"))) -> Clean
A121: ORD-2024-10120 | B121: 45455 | C121: 45462 | D121: CUST-7861 | E121: =PROPER(TRIM([1]raw_orders!E121)) -> Aditi Sen | F121: =PROPER(TRIM([1]raw_orders!F121)) -> Small Business | G121: =IF('[1]Cleaned Text Field'!G121="","Unknown",'[1]Cleaned Text Field'!G121) -> South | H121: =PROPER(TRIM([1]raw_orders!H121)) -> Kerala | I121: =PROPER(TRIM([1]raw_orders!I121)) -> Kochi | J121: =PROPER(TRIM([1]raw_orders!J121)) -> Furniture | K121: =PROPER(TRIM([1]raw_orders!K121)) -> Chairs | L121: Elite Chairs 921 | M121: =IF('[1]Cleaned Text Field'!M121="","Unknown",'[1]Cleaned Text Field'!M121) -> Standard Class | N121: =IF('[1]Cleaned Text Field'!N121="",0,'[1]Cleaned Text Field'!N121) -> 8 | O121: 314.05 | P121: =IF('[1]Cleaned Text Field'!P121="",0,'[1]Cleaned Text Field'!P121) -> 0.25 | Q121: 1884.3 | R121: 1517.69 | S121: 366.61 | T121: =PROPER(TRIM([1]raw_orders!T121)) -> Refunded | U121: =PROPER(TRIM([1]raw_orders!U121)) -> Returned | V121: =IF(Q121=0,0,S121/Q121) -> 0.19456031 | W121: =TEXT(B121,"mmmm") -> June | X121: =YEAR(B121) -> 2024 | Y121: =C121-B121 -> 7 | Z121: =P121 -> 0.25 | AA121: =N121*O121*(1-P121) -> 1884.3 | AB121: =Q121-R121 -> 366.61 | AC121: =IF(OR(B121="",C121="",AA121<=0),"Invalid",IF(Y121<0,"Warning",IF(Z121>100%,"Warning","Clean"))) -> Clean
A122: ORD-2024-10121 | B122: 45514 | C122: 45522 | D122: CUST-6096 | E122: =PROPER(TRIM([1]raw_orders!E122)) -> Sneha Kapoor | F122: =PROPER(TRIM([1]raw_orders!F122)) -> Small Business | G122: =IF('[1]Cleaned Text Field'!G122="","Unknown",'[1]Cleaned Text Field'!G122) -> East | H122: =PROPER(TRIM([1]raw_orders!H122)) -> Bihar | I122: =PROPER(TRIM([1]raw_orders!I122)) -> Patna | J122: =PROPER(TRIM([1]raw_orders!J122)) -> Technology | K122: =PROPER(TRIM([1]raw_orders!K122)) -> Phones | L122: Prime Phones 540 | M122: =IF('[1]Cleaned Text Field'!M122="","Unknown",'[1]Cleaned Text Field'!M122) -> Standard Class | N122: =IF('[1]Cleaned Text Field'!N122="",0,'[1]Cleaned Text Field'!N122) -> 1 | O122: 1823.67 | P122: =IF('[1]Cleaned Text Field'!P122="",0,'[1]Cleaned Text Field'!P122) -> 0.2 | Q122: 1458.94 | R122: 893.2 | S122: 565.74 | T122: =PROPER(TRIM([1]raw_orders!T122)) -> Paid | U122: =PROPER(TRIM([1]raw_orders!U122)) -> Returned | V122: =IF(Q122=0,0,S122/Q122) -> 0.38777469 | W122: =TEXT(B122,"mmmm") -> August | X122: =YEAR(B122) -> 2024 | Y122: =C122-B122 -> 8 | Z122: =P122 -> 0.2 | AA122: =N122*O122*(1-P122) -> 1458.936 | AB122: =Q122-R122 -> 565.74 | AC122: =IF(OR(B122="",C122="",AA122<=0),"Invalid",IF(Y122<0,"Warning",IF(Z122>100%,"Warning","Clean"))) -> Clean
A123: ORD-2025-10122 | B123: 45891 | C123: 45895 | D123: CUST-2044 | E123: =PROPER(TRIM([1]raw_orders!E123)) -> Kabir Singh | F123: =PROPER(TRIM([1]raw_orders!F123)) -> Small Business | G123: =IF('[1]Cleaned Text Field'!G123="","Unknown",'[1]Cleaned Text Field'!G123) -> South | H123: =PROPER(TRIM([1]raw_orders!H123)) -> Andhra Pradesh | I123: =PROPER(TRIM([1]raw_orders!I123)) -> Vijayawada | J123: =PROPER(TRIM([1]raw_orders!J123)) -> Technology | K123: =PROPER(TRIM([1]raw_orders!K123)) -> Machines | L123: Max Machines 948 | M123: =IF('[1]Cleaned Text Field'!M123="","Unknown",'[1]Cleaned Text Field'!M123) -> Second Class | N123: =IF('[1]Cleaned Text Field'!N123="",0,'[1]Cleaned Text Field'!N123) -> 5 | O123: 3482.92 | P123: =IF('[1]Cleaned Text Field'!P123="",0,'[1]Cleaned Text Field'!P123) -> 0 | Q123: 17414.6 | R123: 11760.91 | S123: 5653.69 | T123: =PROPER(TRIM([1]raw_orders!T123)) -> Refunded | U123: =PROPER(TRIM([1]raw_orders!U123)) -> Cancelled | V123: =IF(Q123=0,0,S123/Q123) -> 0.3246523 | W123: =TEXT(B123,"mmmm") -> August | X123: =YEAR(B123) -> 2025 | Y123: =C123-B123 -> 4 | Z123: =P123 -> 0 | AA123: =N123*O123*(1-P123) -> 17414.6 | AB123: =Q123-R123 -> 5653.69 | AC123: =IF(OR(B123="",C123="",AA123<=0),"Invalid",IF(Y123<0,"Warning",IF(Z123>100%,"Warning","Clean"))) -> Clean
A124: ORD-2024-10123 | B124: 45626 | C124: 45394 | D124: CUST-1721 | E124: =PROPER(TRIM([1]raw_orders!E124)) -> Ananya Rao | F124: =PROPER(TRIM([1]raw_orders!F124)) -> Small Business | G124: =IF('[1]Cleaned Text Field'!G124="","Unknown",'[1]Cleaned Text Field'!G124) -> East | H124: =PROPER(TRIM([1]raw_orders!H124)) -> Assam | I124: =PROPER(TRIM([1]raw_orders!I124)) -> Guwahati | J124: =PROPER(TRIM([1]raw_orders!J124)) -> Furniture | K124: =PROPER(TRIM([1]raw_orders!K124)) -> Chairs | L124: Max Chairs 786 | M124: =IF('[1]Cleaned Text Field'!M124="","Unknown",'[1]Cleaned Text Field'!M124) -> Second Class | N124: =IF('[1]Cleaned Text Field'!N124="",0,'[1]Cleaned Text Field'!N124) -> 3 | O124: 170.35 | P124: =IF('[1]Cleaned Text Field'!P124="",0,'[1]Cleaned Text Field'!P124) -> 0 | Q124: 511.05 | R124: 367.18 | S124: 143.87 | T124: =PROPER(TRIM([1]raw_orders!T124)) -> Paid | U124: =PROPER(TRIM([1]raw_orders!U124)) -> Completed | V124: =IF(Q124=0,0,S124/Q124) -> 0.28151844 | W124: =TEXT(B124,"mmmm") -> November | X124: =YEAR(B124) -> 2024 | Y124: =C124-B124 -> -232 | Z124: =P124 -> 0 | AA124: =N124*O124*(1-P124) -> 511.05 | AB124: =Q124-R124 -> 143.87 | AC124: =IF(OR(B124="",C124="",AA124<=0),"Invalid",IF(Y124<0,"Warning",IF(Z124>100%,"Warning","Clean"))) -> Warning
A125: ORD-2024-10124 | B125: 45436 | C125: 45437 | D125: CUST-1007 | E125: =PROPER(TRIM([1]raw_orders!E125)) -> Sneha Kapoor | F125: =PROPER(TRIM([1]raw_orders!F125)) -> Small Business | G125: =IF('[1]Cleaned Text Field'!G125="","Unknown",'[1]Cleaned Text Field'!G125) -> North | H125: =PROPER(TRIM([1]raw_orders!H125)) -> Punjab | I125: =PROPER(TRIM([1]raw_orders!I125)) -> Ludhiana | J125: =PROPER(TRIM([1]raw_orders!J125)) -> Technology | K125: =PROPER(TRIM([1]raw_orders!K125)) -> Copiers | L125: Max Copiers 970 | M125: =IF('[1]Cleaned Text Field'!M125="","Unknown",'[1]Cleaned Text Field'!M125) -> Same Day | N125: =IF('[1]Cleaned Text Field'!N125="",0,'[1]Cleaned Text Field'!N125) -> 1 | O125: 634.13 | P125: =IF('[1]Cleaned Text Field'!P125="",0,'[1]Cleaned Text Field'!P125) -> 0 | Q125: 634.13 | R125: 453.35 | S125: 180.78 | T125: =PROPER(TRIM([1]raw_orders!T125)) -> Refunded | U125: =PROPER(TRIM([1]raw_orders!U125)) -> Cancelled | V125: =IF(Q125=0,0,S125/Q125) -> 0.2850835 | W125: =TEXT(B125,"mmmm") -> May | X125: =YEAR(B125) -> 2024 | Y125: =C125-B125 -> 1 | Z125: =P125 -> 0 | AA125: =N125*O125*(1-P125) -> 634.13 | AB125: =Q125-R125 -> 180.78 | AC125: =IF(OR(B125="",C125="",AA125<=0),"Invalid",IF(Y125<0,"Warning",IF(Z125>100%,"Warning","Clean"))) -> Clean
A126: ORD-2024-10125 | B126: 45494 | C126: 45497 | D126: CUST-4450 | E126: =PROPER(TRIM([1]raw_orders!E126)) -> Isha Nair | F126: =PROPER(TRIM([1]raw_orders!F126)) -> Corporate | G126: =IF('[1]Cleaned Text Field'!G126="","Unknown",'[1]Cleaned Text Field'!G126) -> South | H126: =PROPER(TRIM([1]raw_orders!H126)) -> Karnataka | I126: =PROPER(TRIM([1]raw_orders!I126)) -> Bengaluru | J126: =PROPER(TRIM([1]raw_orders!J126)) -> Technology | K126: =PROPER(TRIM([1]raw_orders!K126)) -> Copiers | L126: Pro Copiers 769 | M126: =IF('[1]Cleaned Text Field'!M126="","Unknown",'[1]Cleaned Text Field'!M126) -> Standard Class | N126: =IF('[1]Cleaned Text Field'!N126="",0,'[1]Cleaned Text Field'!N126) -> 9 | O126: 465.06 | P126: =IF('[1]Cleaned Text Field'!P126="",0,'[1]Cleaned Text Field'!P126) -> -0.15 | Q126: 4185.54 | R126: 3443.74 | S126: 741.8 | T126: =PROPER(TRIM([1]raw_orders!T126)) -> Paid | U126: =PROPER(TRIM([1]raw_orders!U126)) -> Completed | V126: =IF(Q126=0,0,S126/Q126) -> 0.17722922 | W126: =TEXT(B126,"mmmm") -> July | X126: =YEAR(B126) -> 2024 | Y126: =C126-B126 -> 3 | Z126: =P126 -> -0.15 | AA126: =N126*O126*(1-P126) -> 4813.371 | AB126: =Q126-R126 -> 741.8 | AC126: =IF(OR(B126="",C126="",AA126<=0),"Invalid",IF(Y126<0,"Warning",IF(Z126>100%,"Warning","Clean"))) -> Clean
A127: ORD-2025-10126 | B127: 45855 | C127: 45856 | D127: CUST-7924 | E127: =PROPER(TRIM([1]raw_orders!E127)) -> Neha Gupta | F127: =PROPER(TRIM([1]raw_orders!F127)) -> Small Business | G127: =IF('[1]Cleaned Text Field'!G127="","Unknown",'[1]Cleaned Text Field'!G127) -> West | H127: =PROPER(TRIM([1]raw_orders!H127)) -> Rajasthan | I127: =PROPER(TRIM([1]raw_orders!I127)) -> Udaipur | J127: =PROPER(TRIM([1]raw_orders!J127)) -> Furniture | K127: =PROPER(TRIM([1]raw_orders!K127)) -> Tables | L127: Basic Tables 753 | M127: =IF('[1]Cleaned Text Field'!M127="","Unknown",'[1]Cleaned Text Field'!M127) -> Same Day | N127: =IF('[1]Cleaned Text Field'!N127="",0,'[1]Cleaned Text Field'!N127) -> 6 | O127: 3235.27 | P127: =IF('[1]Cleaned Text Field'!P127="",0,'[1]Cleaned Text Field'!P127) -> 0.25 | Q127: 14558.72 | R127: 9591.48 | S127: 4967.24 | T127: =PROPER(TRIM([1]raw_orders!T127)) -> Refunded | U127: =PROPER(TRIM([1]raw_orders!U127)) -> Returned | V127: =IF(Q127=0,0,S127/Q127) -> 0.34118659 | W127: =TEXT(B127,"mmmm") -> July | X127: =YEAR(B127) -> 2025 | Y127: =C127-B127 -> 1 | Z127: =P127 -> 0.25 | AA127: =N127*O127*(1-P127) -> 14558.715 | AB127: =Q127-R127 -> 4967.24 | AC127: =IF(OR(B127="",C127="",AA127<=0),"Invalid",IF(Y127<0,"Warning",IF(Z127>100%,"Warning","Clean"))) -> Clean
A128: ORD-2025-10127 | B128: 45924 | C128: 45926 | D128: CUST-1715 | E128: =PROPER(TRIM([1]raw_orders!E128)) -> Priya Menon | F128: =PROPER(TRIM([1]raw_orders!F128)) -> Corporate | G128: =IF('[1]Cleaned Text Field'!G128="","Unknown",'[1]Cleaned Text Field'!G128) -> North | H128: =PROPER(TRIM([1]raw_orders!H128)) -> Delhi | I128: =PROPER(TRIM([1]raw_orders!I128)) -> New Delhi | J128: =PROPER(TRIM([1]raw_orders!J128)) -> Technology | K128: =PROPER(TRIM([1]raw_orders!K128)) -> Copiers | L128: Prime Copiers 651 | M128: =IF('[1]Cleaned Text Field'!M128="","Unknown",'[1]Cleaned Text Field'!M128) -> Standard Class | N128: =IF('[1]Cleaned Text Field'!N128="",0,'[1]Cleaned Text Field'!N128) -> 3 | O128: 1593.86 | P128: =IF('[1]Cleaned Text Field'!P128="",0,'[1]Cleaned Text Field'!P128) -> 0.1 | Q128: 4303.42 | R128: 2568.57 | S128: 1734.85 | T128: =PROPER(TRIM([1]raw_orders!T128)) -> Paid | U128: =PROPER(TRIM([1]raw_orders!U128)) -> Completed | V128: =IF(Q128=0,0,S128/Q128) -> 0.40313286 | W128: =TEXT(B128,"mmmm") -> September | X128: =YEAR(B128) -> 2025 | Y128: =C128-B128 -> 2 | Z128: =P128 -> 0.1 | AA128: =N128*O128*(1-P128) -> 4303.422 | AB128: =Q128-R128 -> 1734.85 | AC128: =IF(OR(B128="",C128="",AA128<=0),"Invalid",IF(Y128<0,"Warning",IF(Z128>100%,"Warning","Clean"))) -> Clean
A129: ORD-2025-10128 | B129: 45687 | C129: 45683 | D129: CUST-6802 | E129: =PROPER(TRIM([1]raw_orders!E129)) -> Priya Menon | F129: =PROPER(TRIM([1]raw_orders!F129)) -> Corporate | G129: =IF('[1]Cleaned Text Field'!G129="","Unknown",'[1]Cleaned Text Field'!G129) -> West | H129: =PROPER(TRIM([1]raw_orders!H129)) -> Madhya Pradesh | I129: =PROPER(TRIM([1]raw_orders!I129)) -> Indore | J129: =PROPER(TRIM([1]raw_orders!J129)) -> Office Supplies | K129: =PROPER(TRIM([1]raw_orders!K129)) -> Storage | L129: Basic Storage 321 | M129: =IF('[1]Cleaned Text Field'!M129="","Unknown",'[1]Cleaned Text Field'!M129) -> Second Class | N129: =IF('[1]Cleaned Text Field'!N129="",0,'[1]Cleaned Text Field'!N129) -> 2 | O129: 3039.3 | P129: =IF('[1]Cleaned Text Field'!P129="",0,'[1]Cleaned Text Field'!P129) -> 0.05 | Q129: 5774.67 | R129: 3518.36 | S129: 2256.31 | T129: =PROPER(TRIM([1]raw_orders!T129)) -> Paid | U129: =PROPER(TRIM([1]raw_orders!U129)) -> Completed | V129: =IF(Q129=0,0,S129/Q129) -> 0.39072536 | W129: =TEXT(B129,"mmmm") -> January | X129: =YEAR(B129) -> 2025 | Y129: =C129-B129 -> -4 | Z129: =P129 -> 0.05 | AA129: =N129*O129*(1-P129) -> 5774.67 | AB129: =Q129-R129 -> 2256.31 | AC129: =IF(OR(B129="",C129="",AA129<=0),"Invalid",IF(Y129<0,"Warning",IF(Z129>100%,"Warning","Clean"))) -> Warning
A130: ORD-2024-10129 | B130: 45639 | C130: 45642 | D130: CUST-9328 | E130: =PROPER(TRIM([1]raw_orders!E130)) -> Neha Gupta | F130: =PROPER(TRIM([1]raw_orders!F130)) -> Small Business | G130: =IF('[1]Cleaned Text Field'!G130="","Unknown",'[1]Cleaned Text Field'!G130) -> East | H130: =PROPER(TRIM([1]raw_orders!H130)) -> Odisha | I130: =PROPER(TRIM([1]raw_orders!I130)) -> Bhubaneswar | J130: =PROPER(TRIM([1]raw_orders!J130)) -> Furniture | K130: =PROPER(TRIM([1]raw_orders!K130)) -> Furnishings | L130: Prime Furnishings 710 | M130: =IF('[1]Cleaned Text Field'!M130="","Unknown",'[1]Cleaned Text Field'!M130) -> Standard Class | N130: =IF('[1]Cleaned Text Field'!N130="",0,'[1]Cleaned Text Field'!N130) -> 5 | O130: 923.45 | P130: =IF('[1]Cleaned Text Field'!P130="",0,'[1]Cleaned Text Field'!P130) -> 0.05 | Q130: 4386.39 | R130: 3366.88 | S130: 1019.51 | T130: =PROPER(TRIM([1]raw_orders!T130)) -> Paid | U130: =PROPER(TRIM([1]raw_orders!U130)) -> Returned | V130: =IF(Q130=0,0,S130/Q130) -> 0.23242575 | W130: =TEXT(B130,"mmmm") -> December | X130: =YEAR(B130) -> 2024 | Y130: =C130-B130 -> 3 | Z130: =P130 -> 0.05 | AA130: =N130*O130*(1-P130) -> 4386.3875 | AB130: =Q130-R130 -> 1019.51 | AC130: =IF(OR(B130="",C130="",AA130<=0),"Invalid",IF(Y130<0,"Warning",IF(Z130>100%,"Warning","Clean"))) -> Clean
A131: ORD-2024-10130 | B131: 45492 | C131: 45498 | D131: CUST-2588 | E131: =PROPER(TRIM([1]raw_orders!E131)) -> Isha Nair | F131: =PROPER(TRIM([1]raw_orders!F131)) -> Small Business | G131: =IF('[1]Cleaned Text Field'!G131="","Unknown",'[1]Cleaned Text Field'!G131) -> West | H131: =PROPER(TRIM([1]raw_orders!H131)) -> Goa | I131: =PROPER(TRIM([1]raw_orders!I131)) -> Panaji | J131: =PROPER(TRIM([1]raw_orders!J131)) -> Office Supplies | K131: =PROPER(TRIM([1]raw_orders!K131)) -> Binders | L131: Elite Binders 723 | M131: =IF('[1]Cleaned Text Field'!M131="","Unknown",'[1]Cleaned Text Field'!M131) -> Standard Class | N131: =IF('[1]Cleaned Text Field'!N131="",0,'[1]Cleaned Text Field'!N131) -> 7 | O131: 2741.29 | P131: =IF('[1]Cleaned Text Field'!P131="",0,'[1]Cleaned Text Field'!P131) -> 0.05 | Q131: 18229.58 | R131: 15139.15 | S131: 3090.43 | T131: =PROPER(TRIM([1]raw_orders!T131)) -> Paid | U131: =PROPER(TRIM([1]raw_orders!U131)) -> Completed | V131: =IF(Q131=0,0,S131/Q131) -> 0.16952832 | W131: =TEXT(B131,"mmmm") -> July | X131: =YEAR(B131) -> 2024 | Y131: =C131-B131 -> 6 | Z131: =P131 -> 0.05 | AA131: =N131*O131*(1-P131) -> 18229.578 | AB131: =Q131-R131 -> 3090.43 | AC131: =IF(OR(B131="",C131="",AA131<=0),"Invalid",IF(Y131<0,"Warning",IF(Z131>100%,"Warning","Clean"))) -> Clean
... A220: ORD-2025-10219 | B220: 45714 | C220: 45715 | D220: CUST-8270 | E220: =PROPER(TRIM([1]raw_orders!E220)) -> Priya Menon | F220: =PROPER(TRIM([1]raw_orders!F220)) -> Corporate | G220: =IF('[1]Cleaned Text Field'!G220="","Unknown",'[1]Cleaned Text Field'!G220) -> West | H220: =PROPER(TRIM([1]raw_orders!H220)) -> Gujarat | I220: =PROPER(TRIM([1]raw_orders!I220)) -> Ahmedabad | J220: =PROPER(TRIM([1]raw_orders!J220)) -> Furniture | K220: =PROPER(TRIM([1]raw_orders!K220)) -> Bookcases | L220: Classic Bookcases 139 | M220: =IF('[1]Cleaned Text Field'!M220="","Unknown",'[1]Cleaned Text Field'!M220) -> Standard Class | N220: =IF('[1]Cleaned Text Field'!N220="",0,'[1]Cleaned Text Field'!N220) -> 5 | O220: 258.28 | P220: =IF('[1]Cleaned Text Field'!P220="",0,'[1]Cleaned Text Field'!P220) -> 0 | Q220: 1291.4 | R220: 756.93 | S220: 534.47 | T220: =PROPER(TRIM([1]raw_orders!T220)) -> Paid | U220: =PROPER(TRIM([1]raw_orders!U220)) -> Completed | V220: =IF(Q220=0,0,S220/Q220) -> 0.41386867 | W220: =TEXT(B220,"mmmm") -> February | X220: =YEAR(B220) -> 2025 | Y220: =C220-B220 -> 1 | Z220: =P220 -> 0 | AA220: =N220*O220*(1-P220) -> 1291.4 | AB220: =Q220-R220 -> 534.47 | AC220: =IF(OR(B220="",C220="",AA220<=0),"Invalid",IF(Y220<0,"Warning",IF(Z220>100%,"Warning","Clean"))) -> Clean
A221: ORD-2024-10220 | B221: 45461 | C221: 45462 | D221: CUST-1472 | E221: =PROPER(TRIM([1]raw_orders!E221)) -> Rahul Verma | F221: =PROPER(TRIM([1]raw_orders!F221)) -> Consumer | G221: =IF('[1]Cleaned Text Field'!G221="","Unknown",'[1]Cleaned Text Field'!G221) -> East | H221: =PROPER(TRIM([1]raw_orders!H221)) -> Bihar | I221: =PROPER(TRIM([1]raw_orders!I221)) -> Patna | J221: =PROPER(TRIM([1]raw_orders!J221)) -> Technology | K221: =PROPER(TRIM([1]raw_orders!K221)) -> Machines | L221: Elite Machines 290 | M221: =IF('[1]Cleaned Text Field'!M221="","Unknown",'[1]Cleaned Text Field'!M221) -> First Class | N221: =IF('[1]Cleaned Text Field'!N221="",0,'[1]Cleaned Text Field'!N221) -> 2 | O221: 121.49 | P221: =IF('[1]Cleaned Text Field'!P221="",0,'[1]Cleaned Text Field'!P221) -> 85% | Q221: 242.98 | R221: 161.42 | S221: 81.56 | T221: =PROPER(TRIM([1]raw_orders!T221)) -> Paid | U221: =PROPER(TRIM([1]raw_orders!U221)) -> Completed | V221: =IF(Q221=0,0,S221/Q221) -> 0.33566549 | W221: =TEXT(B221,"mmmm") -> June | X221: =YEAR(B221) -> 2024 | Y221: =C221-B221 -> 1 | Z221: =VALUE(SUBSTITUTE(P221,"%",""))/100 -> 0.85 | AA221: =N221*O221*(1-P221) -> 36.447 | AB221: =Q221-R221 -> 81.56 | AC221: =IF(OR(B221="",C221="",AA221<=0),"Invalid",IF(Y221<0,"Warning",IF(Z221>100%,"Warning","Clean"))) -> Clean
A222: ORD-2024-10221 | B222: 45538 | C222: 45538 | D222: CUST-1031 | E222: =PROPER(TRIM([1]raw_orders!E222)) -> Sneha Kapoor | F222: =PROPER(TRIM([1]raw_orders!F222)) -> Consumer | G222: =IF('[1]Cleaned Text Field'!G222="","Unknown",'[1]Cleaned Text Field'!G222) -> South | H222: =PROPER(TRIM([1]raw_orders!H222)) -> Kerala | I222: =PROPER(TRIM([1]raw_orders!I222)) -> Kochi | J222: =PROPER(TRIM([1]raw_orders!J222)) -> Office Supplies | K222: =PROPER(TRIM([1]raw_orders!K222)) -> Storage | L222: Elite Storage 925 | M222: =IF('[1]Cleaned Text Field'!M222="","Unknown",'[1]Cleaned Text Field'!M222) -> First Class | N222: =IF('[1]Cleaned Text Field'!N222="",0,'[1]Cleaned Text Field'!N222) -> 4 | O222: 2810.17 | P222: =IF('[1]Cleaned Text Field'!P222="",0,'[1]Cleaned Text Field'!P222) -> 0.15 | Q222: 9554.58 | R222: 6068.47 | S222: 3486.11 | T222: =PROPER(TRIM([1]raw_orders!T222)) -> Refunded | U222: =PROPER(TRIM([1]raw_orders!U222)) -> Cancelled | V222: =IF(Q222=0,0,S222/Q222) -> 0.36486272 | W222: =TEXT(B222,"mmmm") -> September | X222: =YEAR(B222) -> 2024 | Y222: =C222-B222 -> 0 | Z222: =P222 -> 0.15 | AA222: =N222*O222*(1-P222) -> 9554.578 | AB222: =Q222-R222 -> 3486.11 | AC222: =IF(OR(B222="",C222="",AA222<=0),"Invalid",IF(Y222<0,"Warning",IF(Z222>100%,"Warning","Clean"))) -> Clean
A223: ORD-2025-10222 | B223: 45992 | C223: 45672 | D223: CUST-2495 | E223: =PROPER(TRIM([1]raw_orders!E223)) -> Mira Das | F223: =PROPER(TRIM([1]raw_orders!F223)) -> Corporate | G223: =IF('[1]Cleaned Text Field'!G223="","Unknown",'[1]Cleaned Text Field'!G223) -> South | H223: =PROPER(TRIM([1]raw_orders!H223)) -> Karnataka | I223: =PROPER(TRIM([1]raw_orders!I223)) -> Bengaluru | J223: =PROPER(TRIM([1]raw_orders!J223)) -> Furniture | K223: =PROPER(TRIM([1]raw_orders!K223)) -> Chairs | L223: Classic Chairs 231 | M223: =IF('[1]Cleaned Text Field'!M223="","Unknown",'[1]Cleaned Text Field'!M223) -> Same Day | N223: =IF('[1]Cleaned Text Field'!N223="",0,'[1]Cleaned Text Field'!N223) -> 4 | O223: 1531.53 | P223: =IF('[1]Cleaned Text Field'!P223="",0,'[1]Cleaned Text Field'!P223) -> 0.2 | Q223: 4900.9 | R223: 3552.69 | S223: 1348.21 | T223: =PROPER(TRIM([1]raw_orders!T223)) -> Paid | U223: =PROPER(TRIM([1]raw_orders!U223)) -> Completed | V223: =IF(Q223=0,0,S223/Q223) -> 0.27509437 | W223: =TEXT(B223,"mmmm") -> December | X223: =YEAR(B223) -> 2025 | Y223: =C223-B223 -> -320 | Z223: =P223 -> 0.2 | AA223: =N223*O223*(1-P223) -> 4900.896 | AB223: =Q223-R223 -> 1348.21 | AC223: =IF(OR(B223="",C223="",AA223<=0),"Invalid",IF(Y223<0,"Warning",IF(Z223>100%,"Warning","Clean"))) -> Warning
A224: ORD-2025-10223 | B224: 45776 | C224: 45779 | D224: CUST-4583 | E224: =PROPER(TRIM([1]raw_orders!E224)) -> Vikram Iyer | F224: =PROPER(TRIM([1]raw_orders!F224)) -> Small Business | G224: =IF('[1]Cleaned Text Field'!G224="","Unknown",'[1]Cleaned Text Field'!G224) -> West | H224: =PROPER(TRIM([1]raw_orders!H224)) -> Goa | I224: =PROPER(TRIM([1]raw_orders!I224)) -> Panaji | J224: =PROPER(TRIM([1]raw_orders!J224)) -> Office Supplies | K224: =PROPER(TRIM([1]raw_orders!K224)) -> Storage | L224: Prime Storage 818 | M224: =IF('[1]Cleaned Text Field'!M224="","Unknown",'[1]Cleaned Text Field'!M224) -> First Class | N224: =IF('[1]Cleaned Text Field'!N224="",0,'[1]Cleaned Text Field'!N224) -> 6 | O224: 4308.09 | P224: =IF('[1]Cleaned Text Field'!P224="",0,'[1]Cleaned Text Field'!P224) -> 0 | Q224: 25848.54 | R224: 17729.09 | S224: 8119.45 | T224: =PROPER(TRIM([1]raw_orders!T224)) -> Paid | U224: =PROPER(TRIM([1]raw_orders!U224)) -> Completed | V224: =IF(Q224=0,0,S224/Q224) -> 0.31411639 | W224: =TEXT(B224,"mmmm") -> April | X224: =YEAR(B224) -> 2025 | Y224: =C224-B224 -> 3 | Z224: =P224 -> 0 | AA224: =N224*O224*(1-P224) -> 25848.54 | AB224: =Q224-R224 -> 8119.45 | AC224: =IF(OR(B224="",C224="",AA224<=0),"Invalid",IF(Y224<0,"Warning",IF(Z224>100%,"Warning","Clean"))) -> Clean
A225: ORD-2025-10224 | B225: 45707 | C225: 45714 | D225: CUST-5319 | E225: =PROPER(TRIM([1]raw_orders!E225)) -> Mira Das | F225: =PROPER(TRIM([1]raw_orders!F225)) -> Corporate | G225: =IF('[1]Cleaned Text Field'!G225="","Unknown",'[1]Cleaned Text Field'!G225) -> West | H225: =PROPER(TRIM([1]raw_orders!H225)) -> Maharashtra | I225: =PROPER(TRIM([1]raw_orders!I225)) -> Mumbai | J225: =PROPER(TRIM([1]raw_orders!J225)) -> Furniture | K225: =PROPER(TRIM([1]raw_orders!K225)) -> Furnishings | L225: Elite Furnishings 449 | M225: =IF('[1]Cleaned Text Field'!M225="","Unknown",'[1]Cleaned Text Field'!M225) -> First Class | N225: =IF('[1]Cleaned Text Field'!N225="",0,'[1]Cleaned Text Field'!N225) -> 3 | O225: 490.3 | P225: =IF('[1]Cleaned Text Field'!P225="",0,'[1]Cleaned Text Field'!P225) -> 0.2 | Q225: 1176.72 | R225: 654.33 | S225: 522.39 | T225: =PROPER(TRIM([1]raw_orders!T225)) -> Pending | U225: =PROPER(TRIM([1]raw_orders!U225)) -> Returned | V225: =IF(Q225=0,0,S225/Q225) -> 0.44393739 | W225: =TEXT(B225,"mmmm") -> February | X225: =YEAR(B225) -> 2025 | Y225: =C225-B225 -> 7 | Z225: =P225 -> 0.2 | AA225: =N225*O225*(1-P225) -> 1176.72 | AB225: =Q225-R225 -> 522.39 | AC225: =IF(OR(B225="",C225="",AA225<=0),"Invalid",IF(Y225<0,"Warning",IF(Z225>100%,"Warning","Clean"))) -> Clean
A226: ORD-2025-10225 | B226: 45932 | C226: 45938 | D226: CUST-9871 | E226: =PROPER(TRIM([1]raw_orders!E226)) -> Isha Nair | F226: =PROPER(TRIM([1]raw_orders!F226)) -> Small Business | G226: =IF('[1]Cleaned Text Field'!G226="","Unknown",'[1]Cleaned Text Field'!G226) -> North | H226: =PROPER(TRIM([1]raw_orders!H226)) -> Punjab | I226: =PROPER(TRIM([1]raw_orders!I226)) -> Ludhiana | J226: =PROPER(TRIM([1]raw_orders!J226)) -> Furniture | K226: =PROPER(TRIM([1]raw_orders!K226)) -> Furnishings | L226: Classic Furnishings 109 | M226: =IF('[1]Cleaned Text Field'!M226="","Unknown",'[1]Cleaned Text Field'!M226) -> Standard Class | N226: =IF('[1]Cleaned Text Field'!N226="",0,'[1]Cleaned Text Field'!N226) -> 4 | O226: 3944.64 | P226: =IF('[1]Cleaned Text Field'!P226="",0,'[1]Cleaned Text Field'!P226) -> 0.25 | Q226: 11833.92 | R226: 6682.92 | S226: 5151 | T226: =PROPER(TRIM([1]raw_orders!T226)) -> Paid | U226: =PROPER(TRIM([1]raw_orders!U226)) -> Cancelled | V226: =IF(Q226=0,0,S226/Q226) -> 0.43527419 | W226: =TEXT(B226,"mmmm") -> October | X226: =YEAR(B226) -> 2025 | Y226: =C226-B226 -> 6 | Z226: =P226 -> 0.25 | AA226: =N226*O226*(1-P226) -> 11833.92 | AB226: =Q226-R226 -> 5151 | AC226: =IF(OR(B226="",C226="",AA226<=0),"Invalid",IF(Y226<0,"Warning",IF(Z226>100%,"Warning","Clean"))) -> Clean
A227: ORD-2024-10226 | B227: 45537 | C227: 45545 | D227: CUST-1266 | E227: =PROPER(TRIM([1]raw_orders!E227)) -> Mira Das | F227: =PROPER(TRIM([1]raw_orders!F227)) -> Corporate | G227: =IF('[1]Cleaned Text Field'!G227="","Unknown",'[1]Cleaned Text Field'!G227) -> West | H227: =PROPER(TRIM([1]raw_orders!H227)) -> Goa | I227: =PROPER(TRIM([1]raw_orders!I227)) -> Panaji | J227: =PROPER(TRIM([1]raw_orders!J227)) -> Technology | K227: =PROPER(TRIM([1]raw_orders!K227)) -> Phones | L227: Classic Phones 548 | M227: =IF('[1]Cleaned Text Field'!M227="","Unknown",'[1]Cleaned Text Field'!M227) -> Standard Class | N227: =IF('[1]Cleaned Text Field'!N227="",0,'[1]Cleaned Text Field'!N227) -> 6 | O227: 1032.47 | P227: =IF('[1]Cleaned Text Field'!P227="",0,'[1]Cleaned Text Field'!P227) -> 0.15 | Q227: 5265.6 | R227: 4293.11 | S227: 787.57 | T227: =PROPER(TRIM([1]raw_orders!T227)) -> Paid | U227: =PROPER(TRIM([1]raw_orders!U227)) -> Completed | V227: =IF(Q227=0,0,S227/Q227) -> 0.1495689 | W227: =TEXT(B227,"mmmm") -> September | X227: =YEAR(B227) -> 2024 | Y227: =C227-B227 -> 8 | Z227: =P227 -> 0.15 | AA227: =N227*O227*(1-P227) -> 5265.597 | AB227: =Q227-R227 -> 972.49 | AC227: =IF(OR(B227="",C227="",AA227<=0),"Invalid",IF(Y227<0,"Warning",IF(Z227>100%,"Warning","Clean"))) -> Clean
A228: ORD-2025-10227 | B228: 45934 | C228: 45762 | D228: CUST-2545 | E228: =PROPER(TRIM([1]raw_orders!E228)) -> Diya Patel | F228: =PROPER(TRIM([1]raw_orders!F228)) -> Home Office | G228: =IF('[1]Cleaned Text Field'!G228="","Unknown",'[1]Cleaned Text Field'!G228) -> Unknown | H228: =PROPER(TRIM([1]raw_orders!H228)) -> Kerala | I228: =PROPER(TRIM([1]raw_orders!I228)) -> Kochi | J228: =PROPER(TRIM([1]raw_orders!J228)) -> Technology | K228: =PROPER(TRIM([1]raw_orders!K228)) -> Copiers | L228: Max Copiers 363 | M228: =IF('[1]Cleaned Text Field'!M228="","Unknown",'[1]Cleaned Text Field'!M228) -> Same Day | N228: =IF('[1]Cleaned Text Field'!N228="",0,'[1]Cleaned Text Field'!N228) -> 1 | O228: 2208.27 | P228: =IF('[1]Cleaned Text Field'!P228="",0,'[1]Cleaned Text Field'!P228) -> 0.1 | Q228: 1987.44 | R228: 1110.23 | S228: 877.21 | T228: =PROPER(TRIM([1]raw_orders!T228)) -> Paid | U228: =PROPER(TRIM([1]raw_orders!U228)) -> Completed | V228: =IF(Q228=0,0,S228/Q228) -> 0.44137685 | W228: =TEXT(B228,"mmmm") -> October | X228: =YEAR(B228) -> 2025 | Y228: =C228-B228 -> -172 | Z228: =P228 -> 0.1 | AA228: =N228*O228*(1-P228) -> 1987.443 | AB228: =Q228-R228 -> 877.21 | AC228: =IF(OR(B228="",C228="",AA228<=0),"Invalid",IF(Y228<0,"Warning",IF(Z228>100%,"Warning","Clean"))) -> Warning
A229: ORD-2024-10228 | B229: 45478 | C229: 45485 | D229: CUST-2819 | E229: =PROPER(TRIM([1]raw_orders!E229)) -> Ananya Rao | F229: =PROPER(TRIM([1]raw_orders!F229)) -> Small Business | G229: =IF('[1]Cleaned Text Field'!G229="","Unknown",'[1]Cleaned Text Field'!G229) -> West | H229: =PROPER(TRIM([1]raw_orders!H229)) -> Goa | I229: =PROPER(TRIM([1]raw_orders!I229)) -> Panaji | J229: =PROPER(TRIM([1]raw_orders!J229)) -> Office Supplies | K229: =PROPER(TRIM([1]raw_orders!K229)) -> Binders | L229: Prime Binders 507 | M229: =IF('[1]Cleaned Text Field'!M229="","Unknown",'[1]Cleaned Text Field'!M229) -> First Class | N229: =IF('[1]Cleaned Text Field'!N229="",0,'[1]Cleaned Text Field'!N229) -> 3 | O229: 577.75 | P229: =IF('[1]Cleaned Text Field'!P229="",0,'[1]Cleaned Text Field'!P229) -> 0.15 | Q229: 1473.26 | R229: 899.86 | S229: 573.4 | T229: =PROPER(TRIM([1]raw_orders!T229)) -> Paid | U229: =PROPER(TRIM([1]raw_orders!U229)) -> Completed | V229: =IF(Q229=0,0,S229/Q229) -> 0.38920489 | W229: =TEXT(B229,"mmmm") -> July | X229: =YEAR(B229) -> 2024 | Y229: =C229-B229 -> 7 | Z229: =P229 -> 0.15 | AA229: =N229*O229*(1-P229) -> 1473.2625 | AB229: =Q229-R229 -> 573.4 | AC229: =IF(OR(B229="",C229="",AA229<=0),"Invalid",IF(Y229<0,"Warning",IF(Z229>100%,"Warning","Clean"))) -> Clean
A230: ORD-2024-10229 | B230: 45406 | C230: 45410 | D230: CUST-1076 | E230: =PROPER(TRIM([1]raw_orders!E230)) -> Karan Malhotra | F230: =PROPER(TRIM([1]raw_orders!F230)) -> Small Business | G230: =IF('[1]Cleaned Text Field'!G230="","Unknown",'[1]Cleaned Text Field'!G230) -> South | H230: =PROPER(TRIM([1]raw_orders!H230)) -> Telangana | I230: =PROPER(TRIM([1]raw_orders!I230)) -> Hyderabad | J230: =PROPER(TRIM([1]raw_orders!J230)) -> Office Supplies | K230: =PROPER(TRIM([1]raw_orders!K230)) -> Labels | L230: Smart Labels 914 | M230: =IF('[1]Cleaned Text Field'!M230="","Unknown",'[1]Cleaned Text Field'!M230) -> Second Class | N230: =IF('[1]Cleaned Text Field'!N230="",0,'[1]Cleaned Text Field'!N230) -> 1 | O230: 3194.37 | P230: =IF('[1]Cleaned Text Field'!P230="",0,'[1]Cleaned Text Field'!P230) -> 0.15 | Q230: 2715.21 | R230: 1551.55 | S230: 1163.66 | T230: =PROPER(TRIM([1]raw_orders!T230)) -> Paid | U230: =PROPER(TRIM([1]raw_orders!U230)) -> Completed | V230: =IF(Q230=0,0,S230/Q230) -> 0.4285709 | W230: =TEXT(B230,"mmmm") -> April | X230: =YEAR(B230) -> 2024 | Y230: =C230-B230 -> 4 | Z230: =P230 -> 0.15 | AA230: =N230*O230*(1-P230) -> 2715.2145 | AB230: =Q230-R230 -> 1163.66 | AC230: =IF(OR(B230="",C230="",AA230<=0),"Invalid",IF(Y230<0,"Warning",IF(Z230>100%,"Warning","Clean"))) -> Clean
A231: ORD-2025-10230 | B231: 45836 | C231: 45842 | D231: CUST-1943 | E231: =PROPER(TRIM([1]raw_orders!E231)) -> Rohan Mehta | F231: =PROPER(TRIM([1]raw_orders!F231)) -> Consumer | G231: =IF('[1]Cleaned Text Field'!G231="","Unknown",'[1]Cleaned Text Field'!G231) -> South | H231: =PROPER(TRIM([1]raw_orders!H231)) -> Telangana | I231: =PROPER(TRIM([1]raw_orders!I231)) -> Hyderabad | J231: =PROPER(TRIM([1]raw_orders!J231)) -> Furniture | K231: =PROPER(TRIM([1]raw_orders!K231)) -> Bookcases | L231: Smart Bookcases 662 | M231: =IF('[1]Cleaned Text Field'!M231="","Unknown",'[1]Cleaned Text Field'!M231) -> First Class | N231: =IF('[1]Cleaned Text Field'!N231="",0,'[1]Cleaned Text Field'!N231) -> 3 | O231: 2886.23 | P231: =IF('[1]Cleaned Text Field'!P231="",0,'[1]Cleaned Text Field'!P231) -> 0 | Q231: 8658.69 | R231: 5535.94 | S231: 3122.75 | T231: =PROPER(TRIM([1]raw_orders!T231)) -> Refunded | U231: =PROPER(TRIM([1]raw_orders!U231)) -> Returned | V231: =IF(Q231=0,0,S231/Q231) -> 0.36064924 | W231: =TEXT(B231,"mmmm") -> June | X231: =YEAR(B231) -> 2025 | Y231: =C231-B231 -> 6 | Z231: =P231 -> 0 | AA231: =N231*O231*(1-P231) -> 8658.69 | AB231: =Q231-R231 -> 3122.75 | AC231: =IF(OR(B231="",C231="",AA231<=0),"Invalid",IF(Y231<0,"Warning",IF(Z231>100%,"Warning","Clean"))) -> Clean
A232: ORD-2024-10231 | B232: 45440 | C232: 45357 | D232: CUST-3434 | E232: =PROPER(TRIM([1]raw_orders!E232)) -> Neha Gupta | F232: =PROPER(TRIM([1]raw_orders!F232)) -> Small Business | G232: =IF('[1]Cleaned Text Field'!G232="","Unknown",'[1]Cleaned Text Field'!G232) -> North | H232: =PROPER(TRIM([1]raw_orders!H232)) -> Rajasthan | I232: =PROPER(TRIM([1]raw_orders!I232)) -> Jaipur | J232: =PROPER(TRIM([1]raw_orders!J232)) -> Office Supplies | K232: =PROPER(TRIM([1]raw_orders!K232)) -> Paper | L232: Eco Paper 937 | M232: =IF('[1]Cleaned Text Field'!M232="","Unknown",'[1]Cleaned Text Field'!M232) -> Standard Class | N232: =IF('[1]Cleaned Text Field'!N232="",0,'[1]Cleaned Text Field'!N232) -> 8 | O232: 1540.33 | P232: =IF('[1]Cleaned Text Field'!P232="",0,'[1]Cleaned Text Field'!P232) -> 0.1 | Q232: 11090.38 | R232: 8840.95 | S232: 2249.43 | T232: =PROPER(TRIM([1]raw_orders!T232)) -> Paid | U232: =PROPER(TRIM([1]raw_orders!U232)) -> Completed | V232: =IF(Q232=0,0,S232/Q232) -> 0.20282713 | W232: =TEXT(B232,"mmmm") -> May | X232: =YEAR(B232) -> 2024 | Y232: =C232-B232 -> -83 | Z232: =P232 -> 0.1 | AA232: =N232*O232*(1-P232) -> 11090.376 | AB232: =Q232-R232 -> 2249.43 | AC232: =IF(OR(B232="",C232="",AA232<=0),"Invalid",IF(Y232<0,"Warning",IF(Z232>100%,"Warning","Clean"))) -> Warning
A233: ORD-2024-10232 | B233: 45414 | C233: 45414 | D233: CUST-9139 | E233: =PROPER(TRIM([1]raw_orders!E233)) -> Ananya Rao | F233: =PROPER(TRIM([1]raw_orders!F233)) -> Corporate | G233: =IF('[1]Cleaned Text Field'!G233="","Unknown",'[1]Cleaned Text Field'!G233) -> North | H233: =PROPER(TRIM([1]raw_orders!H233)) -> Rajasthan | I233: =PROPER(TRIM([1]raw_orders!I233)) -> Jaipur | J233: =PROPER(TRIM([1]raw_orders!J233)) -> Office Supplies | K233: =PROPER(TRIM([1]raw_orders!K233)) -> Labels | L233: Max Labels 370 | M233: =IF('[1]Cleaned Text Field'!M233="","Unknown",'[1]Cleaned Text Field'!M233) -> First Class | N233: =IF('[1]Cleaned Text Field'!N233="",0,'[1]Cleaned Text Field'!N233) -> 7 | O233: 2183.38 | P233: =IF('[1]Cleaned Text Field'!P233="",0,'[1]Cleaned Text Field'!P233) -> 0.25 | Q233: 11462.74 | R233: 7163.54 | S233: 4299.2 | T233: =PROPER(TRIM([1]raw_orders!T233)) -> Refunded | U233: =PROPER(TRIM([1]raw_orders!U233)) -> Cancelled | V233: =IF(Q233=0,0,S233/Q233) -> 0.37505867 | W233: =TEXT(B233,"mmmm") -> May | X233: =YEAR(B233) -> 2024 | Y233: =C233-B233 -> 0 | Z233: =P233 -> 0.25 | AA233: =N233*O233*(1-P233) -> 11462.745 | AB233: =Q233-R233 -> 4299.2 | AC233: =IF(OR(B233="",C233="",AA233<=0),"Invalid",IF(Y233<0,"Warning",IF(Z233>100%,"Warning","Clean"))) -> Clean
... A321: ORD-2024-10320 | B321: 45525 | C321: 45529 | D321: CUST-4589 | E321: =PROPER(TRIM([1]raw_orders!E321)) -> Diya Patel | F321: =PROPER(TRIM([1]raw_orders!F321)) -> Consumer | G321: =IF('[1]Cleaned Text Field'!G321="","Unknown",'[1]Cleaned Text Field'!G321) -> West | H321: =PROPER(TRIM([1]raw_orders!H321)) -> Gujarat | I321: =PROPER(TRIM([1]raw_orders!I321)) -> Ahmedabad | J321: =PROPER(TRIM([1]raw_orders!J321)) -> Office Supplies | K321: =PROPER(TRIM([1]raw_orders!K321)) -> Binders | L321: Prime Binders 554 | M321: =IF('[1]Cleaned Text Field'!M321="","Unknown",'[1]Cleaned Text Field'!M321) -> First Class | N321: =IF('[1]Cleaned Text Field'!N321="",0,'[1]Cleaned Text Field'!N321) -> 1 | O321: 270.28 | P321: =IF('[1]Cleaned Text Field'!P321="",0,'[1]Cleaned Text Field'!P321) -> 0 | Q321: 270.28 | R321: 156.34 | S321: 113.94 | T321: =PROPER(TRIM([1]raw_orders!T321)) -> Paid | U321: =PROPER(TRIM([1]raw_orders!U321)) -> Completed | V321: =IF(Q321=0,0,S321/Q321) -> 0.42156282 | W321: =TEXT(B321,"mmmm") -> August | X321: =YEAR(B321) -> 2024 | Y321: =C321-B321 -> 4 | Z321: =P321 -> 0 | AA321: =N321*O321*(1-P321) -> 270.28 | AB321: =Q321-R321 -> 113.94 | AC321: =IF(OR(B321="",C321="",AA321<=0),"Invalid",IF(Y321<0,"Warning",IF(Z321>100%,"Warning","Clean"))) -> Clean
A322: ORD-2024-10321 | B322: 45630 | C322: 45632 | D322: CUST-4667 | E322: =PROPER(TRIM([1]raw_orders!E322)) -> Aarav Sharma | F322: =PROPER(TRIM([1]raw_orders!F322)) -> Home Office | G322: =IF('[1]Cleaned Text Field'!G322="","Unknown",'[1]Cleaned Text Field'!G322) -> East | H322: =PROPER(TRIM([1]raw_orders!H322)) -> West Bengal | I322: =PROPER(TRIM([1]raw_orders!I322)) -> Kolkata | J322: =PROPER(TRIM([1]raw_orders!J322)) -> Office Supplies | K322: =PROPER(TRIM([1]raw_orders!K322)) -> Art | L322: Classic Art 299 | M322: =IF('[1]Cleaned Text Field'!M322="","Unknown",'[1]Cleaned Text Field'!M322) -> Second Class | N322: =IF('[1]Cleaned Text Field'!N322="",0,'[1]Cleaned Text Field'!N322) -> 3 | O322: 876.14 | P322: =IF('[1]Cleaned Text Field'!P322="",0,'[1]Cleaned Text Field'!P322) -> 70% | Q322: 2628.42 | R322: 1541.54 | S322: 1086.88 | T322: =PROPER(TRIM([1]raw_orders!T322)) -> Pending | U322: =PROPER(TRIM([1]raw_orders!U322)) -> Returned | V322: =IF(Q322=0,0,S322/Q322) -> 0.41351078 | W322: =TEXT(B322,"mmmm") -> December | X322: =YEAR(B322) -> 2024 | Y322: =C322-B322 -> 2 | Z322: =VALUE(SUBSTITUTE(P322,"%",""))/100 -> 0.7 | AA322: =N322*O322*(1-P322) -> 788.526 | AB322: =Q322-R322 -> 1086.88 | AC322: =IF(OR(B322="",C322="",AA322<=0),"Invalid",IF(Y322<0,"Warning",IF(Z322>100%,"Warning","Clean"))) -> Clean
A323: ORD-2024-10322 | B323: 45466 | C323: 45473 | D323: CUST-7821 | E323: =PROPER(TRIM([1]raw_orders!E323)) -> Neha Gupta | F323: =PROPER(TRIM([1]raw_orders!F323)) -> Small Business | G323: =IF('[1]Cleaned Text Field'!G323="","Unknown",'[1]Cleaned Text Field'!G323) -> West | H323: =PROPER(TRIM([1]raw_orders!H323)) -> Goa | I323: =PROPER(TRIM([1]raw_orders!I323)) -> Panaji | J323: =PROPER(TRIM([1]raw_orders!J323)) -> Technology | K323: =PROPER(TRIM([1]raw_orders!K323)) -> Accessories | L323: Eco Accessories 220 | M323: =IF('[1]Cleaned Text Field'!M323="","Unknown",'[1]Cleaned Text Field'!M323) -> Same Day | N323: =IF('[1]Cleaned Text Field'!N323="",0,'[1]Cleaned Text Field'!N323) -> 4 | O323: 674.82 | P323: =IF('[1]Cleaned Text Field'!P323="",0,'[1]Cleaned Text Field'!P323) -> 0 | Q323: 2699.28 | R323: 1759.76 | S323: 939.52 | T323: =PROPER(TRIM([1]raw_orders!T323)) -> Failed | U323: =PROPER(TRIM([1]raw_orders!U323)) -> Cancelled | V323: =IF(Q323=0,0,S323/Q323) -> 0.34806319 | W323: =TEXT(B323,"mmmm") -> June | X323: =YEAR(B323) -> 2024 | Y323: =C323-B323 -> 7 | Z323: =P323 -> 0 | AA323: =N323*O323*(1-P323) -> 2699.28 | AB323: =Q323-R323 -> 939.52 | AC323: =IF(OR(B323="",C323="",AA323<=0),"Invalid",IF(Y323<0,"Warning",IF(Z323>100%,"Warning","Clean"))) -> Clean
A324: ORD-2024-10323 | B324: 45608 | C324: 45637 | D324: CUST-8579 | E324: =PROPER(TRIM([1]raw_orders!E324)) -> Isha Nair | F324: =PROPER(TRIM([1]raw_orders!F324)) -> Consumer | G324: =IF('[1]Cleaned Text Field'!G324="","Unknown",'[1]Cleaned Text Field'!G324) -> North | H324: =PROPER(TRIM([1]raw_orders!H324)) -> Uttar Pradesh | I324: =PROPER(TRIM([1]raw_orders!I324)) -> Noida | J324: =PROPER(TRIM([1]raw_orders!J324)) -> Technology | K324: =PROPER(TRIM([1]raw_orders!K324)) -> Phones | L324: Max Phones 422 | M324: =IF('[1]Cleaned Text Field'!M324="","Unknown",'[1]Cleaned Text Field'!M324) -> Second Class | N324: =IF('[1]Cleaned Text Field'!N324="",0,'[1]Cleaned Text Field'!N324) -> 6 | O324: 1369.48 | P324: =IF('[1]Cleaned Text Field'!P324="",0,'[1]Cleaned Text Field'!P324) -> 0.15 | Q324: 6984.35 | R324: 4023.63 | S324: 2960.72 | T324: =PROPER(TRIM([1]raw_orders!T324)) -> Paid | U324: =PROPER(TRIM([1]raw_orders!U324)) -> Completed | V324: =IF(Q324=0,0,S324/Q324) -> 0.42390774 | W324: =TEXT(B324,"mmmm") -> November | X324: =YEAR(B324) -> 2024 | Y324: =C324-B324 -> 29 | Z324: =P324 -> 0.15 | AA324: =N324*O324*(1-P324) -> 6984.348 | AB324: =Q324-R324 -> 2960.72 | AC324: =IF(OR(B324="",C324="",AA324<=0),"Invalid",IF(Y324<0,"Warning",IF(Z324>100%,"Warning","Clean"))) -> Clean
A325: ORD-2024-10324 | B325: 45347 | C325: 45351 | D325: CUST-6909 | E325: =PROPER(TRIM([1]raw_orders!E325)) -> Isha Nair | F325: =PROPER(TRIM([1]raw_orders!F325)) -> Small Business | G325: =IF('[1]Cleaned Text Field'!G325="","Unknown",'[1]Cleaned Text Field'!G325) -> West | H325: =PROPER(TRIM([1]raw_orders!H325)) -> Goa | I325: =PROPER(TRIM([1]raw_orders!I325)) -> Panaji | J325: =PROPER(TRIM([1]raw_orders!J325)) -> Furniture | K325: =PROPER(TRIM([1]raw_orders!K325)) -> Furnishings | L325: Eco Furnishings 897 | M325: =IF('[1]Cleaned Text Field'!M325="","Unknown",'[1]Cleaned Text Field'!M325) -> Standard Class | N325: =IF('[1]Cleaned Text Field'!N325="",0,'[1]Cleaned Text Field'!N325) -> 9 | O325: 1331.46 | P325: =IF('[1]Cleaned Text Field'!P325="",0,'[1]Cleaned Text Field'!P325) -> 0.15 | Q325: 10185.67 | R325: 6479.31 | S325: 3706.36 | T325: =PROPER(TRIM([1]raw_orders!T325)) -> Paid | U325: =PROPER(TRIM([1]raw_orders!U325)) -> Completed | V325: =IF(Q325=0,0,S325/Q325) -> 0.36387984 | W325: =TEXT(B325,"mmmm") -> February | X325: =YEAR(B325) -> 2024 | Y325: =C325-B325 -> 4 | Z325: =P325 -> 0.15 | AA325: =N325*O325*(1-P325) -> 10185.669 | AB325: =Q325-R325 -> 3706.36 | AC325: =IF(OR(B325="",C325="",AA325<=0),"Invalid",IF(Y325<0,"Warning",IF(Z325>100%,"Warning","Clean"))) -> Clean
A326: ORD-2025-10325 | B326: 45869 | C326: 45696 | D326: CUST-7212 | E326: =PROPER(TRIM([1]raw_orders!E326)) -> Rohan Mehta | F326: =PROPER(TRIM([1]raw_orders!F326)) -> Home Office | G326: =IF('[1]Cleaned Text Field'!G326="","Unknown",'[1]Cleaned Text Field'!G326) -> South | H326: =PROPER(TRIM([1]raw_orders!H326)) -> Andhra Pradesh | I326: =PROPER(TRIM([1]raw_orders!I326)) -> Vijayawada | J326: =PROPER(TRIM([1]raw_orders!J326)) -> Office Supplies | K326: =PROPER(TRIM([1]raw_orders!K326)) -> Labels | L326: Basic Labels 102 | M326: =IF('[1]Cleaned Text Field'!M326="","Unknown",'[1]Cleaned Text Field'!M326) -> Same Day | N326: =IF('[1]Cleaned Text Field'!N326="",0,'[1]Cleaned Text Field'!N326) -> 1 | O326: 1947.88 | P326: =IF('[1]Cleaned Text Field'!P326="",0,'[1]Cleaned Text Field'!P326) -> 0.15 | Q326: 1655.7 | R326: 1354.8 | S326: 300.9 | T326: =PROPER(TRIM([1]raw_orders!T326)) -> Paid | U326: =PROPER(TRIM([1]raw_orders!U326)) -> Returned | V326: =IF(Q326=0,0,S326/Q326) -> 0.18173582 | W326: =TEXT(B326,"mmmm") -> July | X326: =YEAR(B326) -> 2025 | Y326: =C326-B326 -> -173 | Z326: =P326 -> 0.15 | AA326: =N326*O326*(1-P326) -> 1655.698 | AB326: =Q326-R326 -> 300.9 | AC326: =IF(OR(B326="",C326="",AA326<=0),"Invalid",IF(Y326<0,"Warning",IF(Z326>100%,"Warning","Clean"))) -> Warning
A327: ORD-2025-10326 | B327: 45916 | C327: 45922 | D327: CUST-7980 | E327: =PROPER(TRIM([1]raw_orders!E327)) -> Sneha Kapoor | F327: =PROPER(TRIM([1]raw_orders!F327)) -> Home Office | G327: =IF('[1]Cleaned Text Field'!G327="","Unknown",'[1]Cleaned Text Field'!G327) -> East | H327: =PROPER(TRIM([1]raw_orders!H327)) -> West Bengal | I327: =PROPER(TRIM([1]raw_orders!I327)) -> Kolkata | J327: =PROPER(TRIM([1]raw_orders!J327)) -> Technology | K327: =PROPER(TRIM([1]raw_orders!K327)) -> Copiers | L327: Prime Copiers 170 | M327: =IF('[1]Cleaned Text Field'!M327="","Unknown",'[1]Cleaned Text Field'!M327) -> Second Class | N327: =IF('[1]Cleaned Text Field'!N327="",0,'[1]Cleaned Text Field'!N327) -> 5 | O327: 3671.2 | P327: =IF('[1]Cleaned Text Field'!P327="",0,'[1]Cleaned Text Field'!P327) -> 0.15 | Q327: 15602.6 | R327: 11908.52 | S327: 3694.08 | T327: =PROPER(TRIM([1]raw_orders!T327)) -> Paid | U327: =PROPER(TRIM([1]raw_orders!U327)) -> Completed | V327: =IF(Q327=0,0,S327/Q327) -> 0.23676054 | W327: =TEXT(B327,"mmmm") -> September | X327: =YEAR(B327) -> 2025 | Y327: =C327-B327 -> 6 | Z327: =P327 -> 0.15 | AA327: =N327*O327*(1-P327) -> 15602.6 | AB327: =Q327-R327 -> 3694.08 | AC327: =IF(OR(B327="",C327="",AA327<=0),"Invalid",IF(Y327<0,"Warning",IF(Z327>100%,"Warning","Clean"))) -> Clean
A328: ORD-2025-10327 | B328: 45860 | C328: 45860 | D328: CUST-1966 | E328: =PROPER(TRIM([1]raw_orders!E328)) -> Sneha Kapoor | F328: =PROPER(TRIM([1]raw_orders!F328)) -> Corporate | G328: =IF('[1]Cleaned Text Field'!G328="","Unknown",'[1]Cleaned Text Field'!G328) -> East | H328: =PROPER(TRIM([1]raw_orders!H328)) -> Jharkhand | I328: =PROPER(TRIM([1]raw_orders!I328)) -> Ranchi | J328: =PROPER(TRIM([1]raw_orders!J328)) -> Furniture | K328: =PROPER(TRIM([1]raw_orders!K328)) -> Furnishings | L328: Smart Furnishings 533 | M328: =IF('[1]Cleaned Text Field'!M328="","Unknown",'[1]Cleaned Text Field'!M328) -> Same Day | N328: =IF('[1]Cleaned Text Field'!N328="",0,'[1]Cleaned Text Field'!N328) -> 5 | O328: 3187.05 | P328: =IF('[1]Cleaned Text Field'!P328="",0,'[1]Cleaned Text Field'!P328) -> 0.05 | Q328: 15138.49 | R328: 11235.72 | S328: 3902.77 | T328: =PROPER(TRIM([1]raw_orders!T328)) -> Paid | U328: =PROPER(TRIM([1]raw_orders!U328)) -> Completed | V328: =IF(Q328=0,0,S328/Q328) -> 0.25780444 | W328: =TEXT(B328,"mmmm") -> July | X328: =YEAR(B328) -> 2025 | Y328: =C328-B328 -> 0 | Z328: =P328 -> 0.05 | AA328: =N328*O328*(1-P328) -> 15138.487 | AB328: =Q328-R328 -> 3902.77 | AC328: =IF(OR(B328="",C328="",AA328<=0),"Invalid",IF(Y328<0,"Warning",IF(Z328>100%,"Warning","Clean"))) -> Clean
A329: ORD-2024-10328 | B329: 45497 | C329: 45500 | D329: CUST-6163 | E329: =PROPER(TRIM([1]raw_orders!E329)) -> Isha Nair | F329: =PROPER(TRIM([1]raw_orders!F329)) -> Consumer | G329: =IF('[1]Cleaned Text Field'!G329="","Unknown",'[1]Cleaned Text Field'!G329) -> West | H329: =PROPER(TRIM([1]raw_orders!H329)) -> Rajasthan | I329: =PROPER(TRIM([1]raw_orders!I329)) -> Udaipur | J329: =PROPER(TRIM([1]raw_orders!J329)) -> Technology | K329: =PROPER(TRIM([1]raw_orders!K329)) -> Accessories | L329: Classic Accessories 489 | M329: =IF('[1]Cleaned Text Field'!M329="","Unknown",'[1]Cleaned Text Field'!M329) -> Second Class | N329: =IF('[1]Cleaned Text Field'!N329="",0,'[1]Cleaned Text Field'!N329) -> 3 | O329: 1834.55 | P329: =IF('[1]Cleaned Text Field'!P329="",0,'[1]Cleaned Text Field'!P329) -> 0.2 | Q329: 4402.92 | R329: 2993.94 | S329: 1408.98 | T329: =PROPER(TRIM([1]raw_orders!T329)) -> Pending | U329: =PROPER(TRIM([1]raw_orders!U329)) -> Cancelled | V329: =IF(Q329=0,0,S329/Q329) -> 0.32001036 | W329: =TEXT(B329,"mmmm") -> July | X329: =YEAR(B329) -> 2024 | Y329: =C329-B329 -> 3 | Z329: =P329 -> 0.2 | AA329: =N329*O329*(1-P329) -> 4402.92 | AB329: =Q329-R329 -> 1408.98 | AC329: =IF(OR(B329="",C329="",AA329<=0),"Invalid",IF(Y329<0,"Warning",IF(Z329>100%,"Warning","Clean"))) -> Clean
A330: ORD-2025-10329 | B330: 45806 | C330: 45812 | D330: CUST-7239 | E330: =PROPER(TRIM([1]raw_orders!E330)) -> Diya Patel | F330: =PROPER(TRIM([1]raw_orders!F330)) -> Consumer | G330: =IF('[1]Cleaned Text Field'!G330="","Unknown",'[1]Cleaned Text Field'!G330) -> West | H330: =PROPER(TRIM([1]raw_orders!H330)) -> Maharashtra | I330: =PROPER(TRIM([1]raw_orders!I330)) -> Mumbai | J330: =PROPER(TRIM([1]raw_orders!J330)) -> Office Supplies | K330: =PROPER(TRIM([1]raw_orders!K330)) -> Storage | L330: Smart Storage 439 | M330: =IF('[1]Cleaned Text Field'!M330="","Unknown",'[1]Cleaned Text Field'!M330) -> First Class | N330: =IF('[1]Cleaned Text Field'!N330="",0,'[1]Cleaned Text Field'!N330) -> 6 | O330: 3100.68 | P330: =IF('[1]Cleaned Text Field'!P330="",0,'[1]Cleaned Text Field'!P330) -> 0 | Q330: 18604.08 | R330: 15834.3 | S330: 2769.78 | T330: =PROPER(TRIM([1]raw_orders!T330)) -> Paid | U330: =PROPER(TRIM([1]raw_orders!U330)) -> Completed | V330: =IF(Q330=0,0,S330/Q330) -> 0.14888025 | W330: =TEXT(B330,"mmmm") -> May | X330: =YEAR(B330) -> 2025 | Y330: =C330-B330 -> 6 | Z330: =P330 -> 0 | AA330: =N330*O330*(1-P330) -> 18604.08 | AB330: =Q330-R330 -> 2769.78 | AC330: =IF(OR(B330="",C330="",AA330<=0),"Invalid",IF(Y330<0,"Warning",IF(Z330>100%,"Warning","Clean"))) -> Clean
A331: ORD-2025-10330 | B331: 45789 | C331: 45795 | D331: CUST-9718 | E331: =PROPER(TRIM([1]raw_orders!E331)) -> Neha Gupta | F331: =PROPER(TRIM([1]raw_orders!F331)) -> Small Business | G331: =IF('[1]Cleaned Text Field'!G331="","Unknown",'[1]Cleaned Text Field'!G331) -> West | H331: =PROPER(TRIM([1]raw_orders!H331)) -> Maharashtra | I331: =PROPER(TRIM([1]raw_orders!I331)) -> Mumbai | J331: =PROPER(TRIM([1]raw_orders!J331)) -> Office Supplies | K331: =PROPER(TRIM([1]raw_orders!K331)) -> Storage | L331: Prime Storage 232 | M331: =IF('[1]Cleaned Text Field'!M331="","Unknown",'[1]Cleaned Text Field'!M331) -> Standard Class | N331: =IF('[1]Cleaned Text Field'!N331="",0,'[1]Cleaned Text Field'!N331) -> 4 | O331: 4053.03 | P331: =IF('[1]Cleaned Text Field'!P331="",0,'[1]Cleaned Text Field'!P331) -> 0.05 | Q331: 15401.51 | R331: 8650.42 | S331: 6751.09 | T331: =PROPER(TRIM([1]raw_orders!T331)) -> Paid | U331: =PROPER(TRIM([1]raw_orders!U331)) -> Completed | V331: =IF(Q331=0,0,S331/Q331) -> 0.43833949 | W331: =TEXT(B331,"mmmm") -> May | X331: =YEAR(B331) -> 2025 | Y331: =C331-B331 -> 6 | Z331: =P331 -> 0.05 | AA331: =N331*O331*(1-P331) -> 15401.514 | AB331: =Q331-R331 -> 6751.09 | AC331: =IF(OR(B331="",C331="",AA331<=0),"Invalid",IF(Y331<0,"Warning",IF(Z331>100%,"Warning","Clean"))) -> Clean
A332: ORD-2024-10331 | B332: 45428 | C332: 45436 | D332: CUST-1116 | E332: =PROPER(TRIM([1]raw_orders!E332)) -> Arjun Bose | F332: =PROPER(TRIM([1]raw_orders!F332)) -> Home Office | G332: =IF('[1]Cleaned Text Field'!G332="","Unknown",'[1]Cleaned Text Field'!G332) -> North | H332: =PROPER(TRIM([1]raw_orders!H332)) -> Punjab | I332: =PROPER(TRIM([1]raw_orders!I332)) -> Ludhiana | J332: =PROPER(TRIM([1]raw_orders!J332)) -> Technology | K332: =PROPER(TRIM([1]raw_orders!K332)) -> Accessories | L332: Prime Accessories 335 | M332: =IF('[1]Cleaned Text Field'!M332="","Unknown",'[1]Cleaned Text Field'!M332) -> Same Day | N332: =IF('[1]Cleaned Text Field'!N332="",0,'[1]Cleaned Text Field'!N332) -> 1 | O332: 783.09 | P332: =IF('[1]Cleaned Text Field'!P332="",0,'[1]Cleaned Text Field'!P332) -> 0 | Q332: 783.09 | R332: 503.89 | S332: 279.2 | T332: =PROPER(TRIM([1]raw_orders!T332)) -> Failed | U332: =PROPER(TRIM([1]raw_orders!U332)) -> Cancelled | V332: =IF(Q332=0,0,S332/Q332) -> 0.35653629 | W332: =TEXT(B332,"mmmm") -> May | X332: =YEAR(B332) -> 2024 | Y332: =C332-B332 -> 8 | Z332: =P332 -> 0 | AA332: =N332*O332*(1-P332) -> 783.09 | AB332: =Q332-R332 -> 279.2 | AC332: =IF(OR(B332="",C332="",AA332<=0),"Invalid",IF(Y332<0,"Warning",IF(Z332>100%,"Warning","Clean"))) -> Clean
A333: ORD-2024-10332 | B333: 45394 | C333: 45632 | D333: CUST-9346 | E333: =PROPER(TRIM([1]raw_orders!E333)) -> Sneha Kapoor | F333: =PROPER(TRIM([1]raw_orders!F333)) -> Home Office | G333: =IF('[1]Cleaned Text Field'!G333="","Unknown",'[1]Cleaned Text Field'!G333) -> East | H333: =PROPER(TRIM([1]raw_orders!H333)) -> Odisha | I333: =PROPER(TRIM([1]raw_orders!I333)) -> Bhubaneswar | J333: =PROPER(TRIM([1]raw_orders!J333)) -> Office Supplies | K333: =PROPER(TRIM([1]raw_orders!K333)) -> Binders | L333: Smart Binders 939 | M333: =IF('[1]Cleaned Text Field'!M333="","Unknown",'[1]Cleaned Text Field'!M333) -> Second Class | N333: =IF('[1]Cleaned Text Field'!N333="",0,'[1]Cleaned Text Field'!N333) -> 4 | O333: 2685.66 | P333: =IF('[1]Cleaned Text Field'!P333="",0,'[1]Cleaned Text Field'!P333) -> 0 | Q333: 10742.64 | R333: 6477.37 | S333: 4265.27 | T333: =PROPER(TRIM([1]raw_orders!T333)) -> Paid | U333: =PROPER(TRIM([1]raw_orders!U333)) -> Returned | V333: =IF(Q333=0,0,S333/Q333) -> 0.39704114 | W333: =TEXT(B333,"mmmm") -> April | X333: =YEAR(B333) -> 2024 | Y333: =C333-B333 -> 238 | Z333: =P333 -> 0 | AA333: =N333*O333*(1-P333) -> 10742.64 | AB333: =Q333-R333 -> 4265.27 | AC333: =IF(OR(B333="",C333="",AA333<=0),"Invalid",IF(Y333<0,"Warning",IF(Z333>100%,"Warning","Clean"))) -> Clean
A334: ORD-2025-10333 | B334: 45804 | C334: 45805 | D334: CUST-5332 | E334: =PROPER(TRIM([1]raw_orders!E334)) -> Aarav Sharma | F334: =PROPER(TRIM([1]raw_orders!F334)) -> Consumer | G334: =IF('[1]Cleaned Text Field'!G334="","Unknown",'[1]Cleaned Text Field'!G334) -> South | H334: =PROPER(TRIM([1]raw_orders!H334)) -> Andhra Pradesh | I334: =PROPER(TRIM([1]raw_orders!I334)) -> Vijayawada | J334: =PROPER(TRIM([1]raw_orders!J334)) -> Technology | K334: =PROPER(TRIM([1]raw_orders!K334)) -> Machines | L334: Basic Machines 601 | M334: =IF('[1]Cleaned Text Field'!M334="","Unknown",'[1]Cleaned Text Field'!M334) -> Second Class | N334: =IF('[1]Cleaned Text Field'!N334="",0,'[1]Cleaned Text Field'!N334) -> 2 | O334: 3911.96 | P334: =IF('[1]Cleaned Text Field'!P334="",0,'[1]Cleaned Text Field'!P334) -> 0 | Q334: 7823.92 | R334: 6034.63 | S334: 1789.29 | T334: =PROPER(TRIM([1]raw_orders!T334)) -> Paid | U334: =PROPER(TRIM([1]raw_orders!U334)) -> Completed | V334: =IF(Q334=0,0,S334/Q334) -> 0.22869482 | W334: =TEXT(B334,"mmmm") -> May | X334: =YEAR(B334) -> 2025 | Y334: =C334-B334 -> 1 | Z334: =P334 -> 0 | AA334: =N334*O334*(1-P334) -> 7823.92 | AB334: =Q334-R334 -> 1789.29 | AC334: =IF(OR(B334="",C334="",AA334<=0),"Invalid",IF(Y334<0,"Warning",IF(Z334>100%,"Warning","Clean"))) -> Clean
... A482: ORD-2025-10481 | B482: 45662 | C482: 45666 | D482: CUST-9947 | E482: =PROPER(TRIM([1]raw_orders!E482)) -> Neha Gupta | F482: =PROPER(TRIM([1]raw_orders!F482)) -> Small Business | G482: =IF('[1]Cleaned Text Field'!G482="","Unknown",'[1]Cleaned Text Field'!G482) -> South | H482: =PROPER(TRIM([1]raw_orders!H482)) -> Tamil Nadu | I482: =PROPER(TRIM([1]raw_orders!I482)) -> Chennai | J482: =PROPER(TRIM([1]raw_orders!J482)) -> Office Supplies | K482: =PROPER(TRIM([1]raw_orders!K482)) -> Storage | L482: Eco Storage 923 | M482: =IF('[1]Cleaned Text Field'!M482="","Unknown",'[1]Cleaned Text Field'!M482) -> Unknown | N482: =IF('[1]Cleaned Text Field'!N482="",0,'[1]Cleaned Text Field'!N482) -> 5 | O482: 905.16 | P482: =IF('[1]Cleaned Text Field'!P482="",0,'[1]Cleaned Text Field'!P482) -> 0 | Q482: 4525.8 | R482: 2714.51 | S482: 1811.29 | T482: =PROPER(TRIM([1]raw_orders!T482)) -> Paid | U482: =PROPER(TRIM([1]raw_orders!U482)) -> Completed | V482: =IF(Q482=0,0,S482/Q482) -> 0.40021433 | W482: =TEXT(B482,"mmmm") -> January | X482: =YEAR(B482) -> 2025 | Y482: =C482-B482 -> 4 | Z482: =P482 -> 0 | AA482: =N482*O482*(1-P482) -> 4525.8 | AB482: =Q482-R482 -> 1811.29 | AC482: =IF(OR(B482="",C482="",AA482<=0),"Invalid",IF(Y482<0,"Warning",IF(Z482>100%,"Warning","Clean"))) -> Clean
A483: ORD-2025-10482 | B483: 45813 | C483: 45821 | D483: CUST-4403 | E483: =PROPER(TRIM([1]raw_orders!E483)) -> Isha Nair | F483: =PROPER(TRIM([1]raw_orders!F483)) -> Consumer | G483: =IF('[1]Cleaned Text Field'!G483="","Unknown",'[1]Cleaned Text Field'!G483) -> North | H483: =PROPER(TRIM([1]raw_orders!H483)) -> Uttar Pradesh | I483: =PROPER(TRIM([1]raw_orders!I483)) -> Noida | J483: =PROPER(TRIM([1]raw_orders!J483)) -> Technology | K483: =PROPER(TRIM([1]raw_orders!K483)) -> Machines | L483: Classic Machines 287 | M483: =IF('[1]Cleaned Text Field'!M483="","Unknown",'[1]Cleaned Text Field'!M483) -> Same Day | N483: =IF('[1]Cleaned Text Field'!N483="",0,'[1]Cleaned Text Field'!N483) -> 4 | O483: 2793.88 | P483: =IF('[1]Cleaned Text Field'!P483="",0,'[1]Cleaned Text Field'!P483) -> 85% | Q483: 10616.74 | R483: 6353.59 | S483: 4263.15 | T483: =PROPER(TRIM([1]raw_orders!T483)) -> Paid | U483: =PROPER(TRIM([1]raw_orders!U483)) -> Completed | V483: =IF(Q483=0,0,S483/Q483) -> 0.40154982 | W483: =TEXT(B483,"mmmm") -> June | X483: =YEAR(B483) -> 2025 | Y483: =C483-B483 -> 8 | Z483: =VALUE(SUBSTITUTE(P483,"%",""))/100 -> 0.85 | AA483: =N483*O483*(1-P483) -> 1676.328 | AB483: =Q483-R483 -> 4263.15 | AC483: =IF(OR(B483="",C483="",AA483<=0),"Invalid",IF(Y483<0,"Warning",IF(Z483>100%,"Warning","Clean"))) -> Clean
A484: ORD-2024-10483 | B484: 45495 | C484: 45495 | D484: CUST-3583 | E484: =PROPER(TRIM([1]raw_orders!E484)) -> Priya Menon | F484: =PROPER(TRIM([1]raw_orders!F484)) -> Consumer | G484: =IF('[1]Cleaned Text Field'!G484="","Unknown",'[1]Cleaned Text Field'!G484) -> South | H484: =PROPER(TRIM([1]raw_orders!H484)) -> Karnataka | I484: =PROPER(TRIM([1]raw_orders!I484)) -> Bengaluru | J484: =PROPER(TRIM([1]raw_orders!J484)) -> Technology | K484: =PROPER(TRIM([1]raw_orders!K484)) -> Accessories | L484: Basic Accessories 518 | M484: =IF('[1]Cleaned Text Field'!M484="","Unknown",'[1]Cleaned Text Field'!M484) -> Second Class | N484: =IF('[1]Cleaned Text Field'!N484="",0,'[1]Cleaned Text Field'!N484) -> 3 | O484: 1286.22 | P484: =IF('[1]Cleaned Text Field'!P484="",0,'[1]Cleaned Text Field'!P484) -> 0.25 | Q484: 2893.99 | R484: 1856.03 | S484: 1037.96 | T484: =PROPER(TRIM([1]raw_orders!T484)) -> Paid | U484: =PROPER(TRIM([1]raw_orders!U484)) -> Completed | V484: =IF(Q484=0,0,S484/Q484) -> 0.35866053 | W484: =TEXT(B484,"mmmm") -> July | X484: =YEAR(B484) -> 2024 | Y484: =C484-B484 -> 0 | Z484: =P484 -> 0.25 | AA484: =N484*O484*(1-P484) -> 2893.995 | AB484: =Q484-R484 -> 1037.96 | AC484: =IF(OR(B484="",C484="",AA484<=0),"Invalid",IF(Y484<0,"Warning",IF(Z484>100%,"Warning","Clean"))) -> Clean
A485: ORD-2024-10484 | B485: 45651 | C485: 45651 | D485: CUST-9432 | E485: =PROPER(TRIM([1]raw_orders!E485)) -> Mira Das | F485: =PROPER(TRIM([1]raw_orders!F485)) -> Corporate | G485: =IF('[1]Cleaned Text Field'!G485="","Unknown",'[1]Cleaned Text Field'!G485) -> East | H485: =PROPER(TRIM([1]raw_orders!H485)) -> Bihar | I485: =PROPER(TRIM([1]raw_orders!I485)) -> Patna | J485: =PROPER(TRIM([1]raw_orders!J485)) -> Technology | K485: =PROPER(TRIM([1]raw_orders!K485)) -> Copiers | L485: Pro Copiers 984 | M485: =IF('[1]Cleaned Text Field'!M485="","Unknown",'[1]Cleaned Text Field'!M485) -> Standard Class | N485: =IF('[1]Cleaned Text Field'!N485="",0,'[1]Cleaned Text Field'!N485) -> 1 | O485: 829.66 | P485: =IF('[1]Cleaned Text Field'!P485="",0,'[1]Cleaned Text Field'!P485) -> 0.15 | Q485: 705.21 | R485: 438.32 | S485: 266.89 | T485: =PROPER(TRIM([1]raw_orders!T485)) -> Paid | U485: =PROPER(TRIM([1]raw_orders!U485)) -> Completed | V485: =IF(Q485=0,0,S485/Q485) -> 0.37845464 | W485: =TEXT(B485,"mmmm") -> December | X485: =YEAR(B485) -> 2024 | Y485: =C485-B485 -> 0 | Z485: =P485 -> 0.15 | AA485: =N485*O485*(1-P485) -> 705.211 | AB485: =Q485-R485 -> 266.89 | AC485: =IF(OR(B485="",C485="",AA485<=0),"Invalid",IF(Y485<0,"Warning",IF(Z485>100%,"Warning","Clean"))) -> Clean
A486: ORD-2024-10485 | B486: 45654 | C486: 45657 | D486: CUST-1801 | E486: =PROPER(TRIM([1]raw_orders!E486)) -> Mira Das | F486: =PROPER(TRIM([1]raw_orders!F486)) -> Small Business | G486: =IF('[1]Cleaned Text Field'!G486="","Unknown",'[1]Cleaned Text Field'!G486) -> South | H486: =PROPER(TRIM([1]raw_orders!H486)) -> Andhra Pradesh | I486: =PROPER(TRIM([1]raw_orders!I486)) -> Vijayawada | J486: =PROPER(TRIM([1]raw_orders!J486)) -> Furniture | K486: =PROPER(TRIM([1]raw_orders!K486)) -> Furnishings | L486: Max Furnishings 297 | M486: =IF('[1]Cleaned Text Field'!M486="","Unknown",'[1]Cleaned Text Field'!M486) -> First Class | N486: =IF('[1]Cleaned Text Field'!N486="",0,'[1]Cleaned Text Field'!N486) -> 6 | O486: 3641.22 | P486: =IF('[1]Cleaned Text Field'!P486="",0,'[1]Cleaned Text Field'!P486) -> 0.25 | Q486: 16385.49 | R486: 13679.24 | S486: 2706.25 | T486: =PROPER(TRIM([1]raw_orders!T486)) -> Paid | U486: =PROPER(TRIM([1]raw_orders!U486)) -> Completed | V486: =IF(Q486=0,0,S486/Q486) -> 0.16516137 | W486: =TEXT(B486,"mmmm") -> December | X486: =YEAR(B486) -> 2024 | Y486: =C486-B486 -> 3 | Z486: =P486 -> 0.25 | AA486: =N486*O486*(1-P486) -> 16385.49 | AB486: =Q486-R486 -> 2706.25 | AC486: =IF(OR(B486="",C486="",AA486<=0),"Invalid",IF(Y486<0,"Warning",IF(Z486>100%,"Warning","Clean"))) -> Clean
A487: ORD-2025-10486 | B487: 45679 | C487: 45680 | D487: CUST-1594 | E487: =PROPER(TRIM([1]raw_orders!E487)) -> Rahul Verma | F487: =PROPER(TRIM([1]raw_orders!F487)) -> Corporate | G487: =IF('[1]Cleaned Text Field'!G487="","Unknown",'[1]Cleaned Text Field'!G487) -> West | H487: =PROPER(TRIM([1]raw_orders!H487)) -> Goa | I487: =PROPER(TRIM([1]raw_orders!I487)) -> Panaji | J487: =PROPER(TRIM([1]raw_orders!J487)) -> Furniture | K487: =PROPER(TRIM([1]raw_orders!K487)) -> Bookcases | L487: Elite Bookcases 802 | M487: =IF('[1]Cleaned Text Field'!M487="","Unknown",'[1]Cleaned Text Field'!M487) -> Standard Class | N487: =IF('[1]Cleaned Text Field'!N487="",0,'[1]Cleaned Text Field'!N487) -> 4 | O487: 2555.19 | P487: =IF('[1]Cleaned Text Field'!P487="",0,'[1]Cleaned Text Field'!P487) -> 0.25 | Q487: 7665.57 | R487: 5595.6 | S487: 2069.97 | T487: =PROPER(TRIM([1]raw_orders!T487)) -> Paid | U487: =PROPER(TRIM([1]raw_orders!U487)) -> Completed | V487: =IF(Q487=0,0,S487/Q487) -> 0.27003471 | W487: =TEXT(B487,"mmmm") -> January | X487: =YEAR(B487) -> 2025 | Y487: =C487-B487 -> 1 | Z487: =P487 -> 0.25 | AA487: =N487*O487*(1-P487) -> 7665.57 | AB487: =Q487-R487 -> 2069.97 | AC487: =IF(OR(B487="",C487="",AA487<=0),"Invalid",IF(Y487<0,"Warning",IF(Z487>100%,"Warning","Clean"))) -> Clean
A488: ORD-2025-10487 | B488: 45830 | C488: 45834 | D488: CUST-8132 | E488: =PROPER(TRIM([1]raw_orders!E488)) -> Rahul Verma | F488: =PROPER(TRIM([1]raw_orders!F488)) -> Corporate | G488: =IF('[1]Cleaned Text Field'!G488="","Unknown",'[1]Cleaned Text Field'!G488) -> West | H488: =PROPER(TRIM([1]raw_orders!H488)) -> Goa | I488: =PROPER(TRIM([1]raw_orders!I488)) -> Panaji | J488: =PROPER(TRIM([1]raw_orders!J488)) -> Furniture | K488: =PROPER(TRIM([1]raw_orders!K488)) -> Tables | L488: Pro Tables 257 | M488: =IF('[1]Cleaned Text Field'!M488="","Unknown",'[1]Cleaned Text Field'!M488) -> Standard Class | N488: =IF('[1]Cleaned Text Field'!N488="",0,'[1]Cleaned Text Field'!N488) -> 3 | O488: 1946.18 | P488: =IF('[1]Cleaned Text Field'!P488="",0,'[1]Cleaned Text Field'!P488) -> 0.2 | Q488: 4670.83 | R488: 3166.49 | S488: 1504.34 | T488: =PROPER(TRIM([1]raw_orders!T488)) -> Paid | U488: =PROPER(TRIM([1]raw_orders!U488)) -> Completed | V488: =IF(Q488=0,0,S488/Q488) -> 0.32207124 | W488: =TEXT(B488,"mmmm") -> June | X488: =YEAR(B488) -> 2025 | Y488: =C488-B488 -> 4 | Z488: =P488 -> 0.2 | AA488: =N488*O488*(1-P488) -> 4670.832 | AB488: =Q488-R488 -> 1504.34 | AC488: =IF(OR(B488="",C488="",AA488<=0),"Invalid",IF(Y488<0,"Warning",IF(Z488>100%,"Warning","Clean"))) -> Clean
A489: ORD-2025-10488 | B489: 45818 | C489: 45825 | D489: CUST-7685 | E489: =PROPER(TRIM([1]raw_orders!E489)) -> Rahul Verma | F489: =PROPER(TRIM([1]raw_orders!F489)) -> Corporate | G489: =IF('[1]Cleaned Text Field'!G489="","Unknown",'[1]Cleaned Text Field'!G489) -> South | H489: =PROPER(TRIM([1]raw_orders!H489)) -> Telangana | I489: =PROPER(TRIM([1]raw_orders!I489)) -> Hyderabad | J489: =PROPER(TRIM([1]raw_orders!J489)) -> Furniture | K489: =PROPER(TRIM([1]raw_orders!K489)) -> Furnishings | L489: Prime Furnishings 299 | M489: =IF('[1]Cleaned Text Field'!M489="","Unknown",'[1]Cleaned Text Field'!M489) -> Standard Class | N489: =IF('[1]Cleaned Text Field'!N489="",0,'[1]Cleaned Text Field'!N489) -> 5 | O489: 1231.1 | P489: =IF('[1]Cleaned Text Field'!P489="",0,'[1]Cleaned Text Field'!P489) -> 0 | Q489: 6155.5 | R489: 4282.09 | S489: 1873.41 | T489: =PROPER(TRIM([1]raw_orders!T489)) -> Refunded | U489: =PROPER(TRIM([1]raw_orders!U489)) -> Returned | V489: =IF(Q489=0,0,S489/Q489) -> 0.30434733 | W489: =TEXT(B489,"mmmm") -> June | X489: =YEAR(B489) -> 2025 | Y489: =C489-B489 -> 7 | Z489: =P489 -> 0 | AA489: =N489*O489*(1-P489) -> 6155.5 | AB489: =Q489-R489 -> 1873.41 | AC489: =IF(OR(B489="",C489="",AA489<=0),"Invalid",IF(Y489<0,"Warning",IF(Z489>100%,"Warning","Clean"))) -> Clean
A490: ORD-2024-10489 | B490: 45579 | C490: 45585 | D490: CUST-2183 | E490: =PROPER(TRIM([1]raw_orders!E490)) -> Aditi Sen | F490: =PROPER(TRIM([1]raw_orders!F490)) -> Small Business | G490: =IF('[1]Cleaned Text Field'!G490="","Unknown",'[1]Cleaned Text Field'!G490) -> North | H490: =PROPER(TRIM([1]raw_orders!H490)) -> Rajasthan | I490: =PROPER(TRIM([1]raw_orders!I490)) -> Jaipur | J490: =PROPER(TRIM([1]raw_orders!J490)) -> Furniture | K490: =PROPER(TRIM([1]raw_orders!K490)) -> Tables | L490: Eco Tables 487 | M490: =IF('[1]Cleaned Text Field'!M490="","Unknown",'[1]Cleaned Text Field'!M490) -> Same Day | N490: =IF('[1]Cleaned Text Field'!N490="",0,'[1]Cleaned Text Field'!N490) -> 7 | O490: 1547.6 | P490: =IF('[1]Cleaned Text Field'!P490="",0,'[1]Cleaned Text Field'!P490) -> 0.2 | Q490: 8666.56 | R490: 5967.44 | S490: 2699.12 | T490: =PROPER(TRIM([1]raw_orders!T490)) -> Paid | U490: =PROPER(TRIM([1]raw_orders!U490)) -> Completed | V490: =IF(Q490=0,0,S490/Q490) -> 0.31144076 | W490: =TEXT(B490,"mmmm") -> October | X490: =YEAR(B490) -> 2024 | Y490: =C490-B490 -> 6 | Z490: =P490 -> 0.2 | AA490: =N490*O490*(1-P490) -> 8666.56 | AB490: =Q490-R490 -> 2699.12 | AC490: =IF(OR(B490="",C490="",AA490<=0),"Invalid",IF(Y490<0,"Warning",IF(Z490>100%,"Warning","Clean"))) -> Clean
A491: ORD-2024-10490 | B491: 45329 | C491: 45334 | D491: CUST-1636 | E491: =PROPER(TRIM([1]raw_orders!E491)) -> Arjun Bose | F491: =PROPER(TRIM([1]raw_orders!F491)) -> Home Office | G491: =IF('[1]Cleaned Text Field'!G491="","Unknown",'[1]Cleaned Text Field'!G491) -> East | H491: =PROPER(TRIM([1]raw_orders!H491)) -> West Bengal | I491: =PROPER(TRIM([1]raw_orders!I491)) -> Kolkata | J491: =PROPER(TRIM([1]raw_orders!J491)) -> Technology | K491: =PROPER(TRIM([1]raw_orders!K491)) -> Accessories | L491: Prime Accessories 960 | M491: =IF('[1]Cleaned Text Field'!M491="","Unknown",'[1]Cleaned Text Field'!M491) -> Second Class | N491: =IF('[1]Cleaned Text Field'!N491="",0,'[1]Cleaned Text Field'!N491) -> 1 | O491: 452.19 | P491: =IF('[1]Cleaned Text Field'!P491="",0,'[1]Cleaned Text Field'!P491) -> 0.2 | Q491: 361.75 | R491: 262.53 | S491: 99.22 | T491: =PROPER(TRIM([1]raw_orders!T491)) -> Paid | U491: =PROPER(TRIM([1]raw_orders!U491)) -> Completed | V491: =IF(Q491=0,0,S491/Q491) -> 0.27427782 | W491: =TEXT(B491,"mmmm") -> February | X491: =YEAR(B491) -> 2024 | Y491: =C491-B491 -> 5 | Z491: =P491 -> 0.2 | AA491: =N491*O491*(1-P491) -> 361.752 | AB491: =Q491-R491 -> 99.22 | AC491: =IF(OR(B491="",C491="",AA491<=0),"Invalid",IF(Y491<0,"Warning",IF(Z491>100%,"Warning","Clean"))) -> Clean
A492: ORD-2024-10491 | B492: 45551 | C492: 45554 | D492: CUST-1350 | E492: =PROPER(TRIM([1]raw_orders!E492)) -> Aditi Sen | F492: =PROPER(TRIM([1]raw_orders!F492)) -> Consumer | G492: =IF('[1]Cleaned Text Field'!G492="","Unknown",'[1]Cleaned Text Field'!G492) -> West | H492: =PROPER(TRIM([1]raw_orders!H492)) -> Rajasthan | I492: =PROPER(TRIM([1]raw_orders!I492)) -> Udaipur | J492: =PROPER(TRIM([1]raw_orders!J492)) -> Office Supplies | K492: =PROPER(TRIM([1]raw_orders!K492)) -> Binders | L492: Smart Binders 191 | M492: =IF('[1]Cleaned Text Field'!M492="","Unknown",'[1]Cleaned Text Field'!M492) -> First Class | N492: =IF('[1]Cleaned Text Field'!N492="",0,'[1]Cleaned Text Field'!N492) -> 7 | O492: 406.42 | P492: =IF('[1]Cleaned Text Field'!P492="",0,'[1]Cleaned Text Field'!P492) -> 0.15 | Q492: 2418.2 | R492: 1613.82 | S492: 804.38 | T492: =PROPER(TRIM([1]raw_orders!T492)) -> Paid | U492: =PROPER(TRIM([1]raw_orders!U492)) -> Completed | V492: =IF(Q492=0,0,S492/Q492) -> 0.33263584 | W492: =TEXT(B492,"mmmm") -> September | X492: =YEAR(B492) -> 2024 | Y492: =C492-B492 -> 3 | Z492: =P492 -> 0.15 | AA492: =N492*O492*(1-P492) -> 2418.199 | AB492: =Q492-R492 -> 804.38 | AC492: =IF(OR(B492="",C492="",AA492<=0),"Invalid",IF(Y492<0,"Warning",IF(Z492>100%,"Warning","Clean"))) -> Clean
A493: ORD-2025-10492 | B493: 45776 | C493: 45777 | D493: CUST-4101 | E493: =PROPER(TRIM([1]raw_orders!E493)) -> Mira Das | F493: =PROPER(TRIM([1]raw_orders!F493)) -> Corporate | G493: =IF('[1]Cleaned Text Field'!G493="","Unknown",'[1]Cleaned Text Field'!G493) -> South | H493: =PROPER(TRIM([1]raw_orders!H493)) -> Kerala | I493: =PROPER(TRIM([1]raw_orders!I493)) -> Kochi | J493: =PROPER(TRIM([1]raw_orders!J493)) -> Technology | K493: =PROPER(TRIM([1]raw_orders!K493)) -> Accessories | L493: Prime Accessories 118 | M493: =IF('[1]Cleaned Text Field'!M493="","Unknown",'[1]Cleaned Text Field'!M493) -> Standard Class | N493: =IF('[1]Cleaned Text Field'!N493="",0,'[1]Cleaned Text Field'!N493) -> 4 | O493: 606.58 | P493: =IF('[1]Cleaned Text Field'!P493="",0,'[1]Cleaned Text Field'!P493) -> 0.2 | Q493: 1941.06 | R493: 1207.42 | S493: 733.64 | T493: =PROPER(TRIM([1]raw_orders!T493)) -> Paid | U493: =PROPER(TRIM([1]raw_orders!U493)) -> Completed | V493: =IF(Q493=0,0,S493/Q493) -> 0.37795844 | W493: =TEXT(B493,"mmmm") -> April | X493: =YEAR(B493) -> 2025 | Y493: =C493-B493 -> 1 | Z493: =P493 -> 0.2 | AA493: =N493*O493*(1-P493) -> 1941.056 | AB493: =Q493-R493 -> 733.64 | AC493: =IF(OR(B493="",C493="",AA493<=0),"Invalid",IF(Y493<0,"Warning",IF(Z493>100%,"Warning","Clean"))) -> Clean
A494: ORD-2025-10493 | B494: 45836 | C494: 45840 | D494: CUST-4679 | E494: =PROPER(TRIM([1]raw_orders!E494)) -> Ananya Rao | F494: =PROPER(TRIM([1]raw_orders!F494)) -> Corporate | G494: =IF('[1]Cleaned Text Field'!G494="","Unknown",'[1]Cleaned Text Field'!G494) -> South | H494: =PROPER(TRIM([1]raw_orders!H494)) -> Andhra Pradesh | I494: =PROPER(TRIM([1]raw_orders!I494)) -> Vijayawada | J494: =PROPER(TRIM([1]raw_orders!J494)) -> Office Supplies | K494: =PROPER(TRIM([1]raw_orders!K494)) -> Storage | L494: Elite Storage 331 | M494: =IF('[1]Cleaned Text Field'!M494="","Unknown",'[1]Cleaned Text Field'!M494) -> Second Class | N494: =IF('[1]Cleaned Text Field'!N494="",0,'[1]Cleaned Text Field'!N494) -> 2 | O494: 2725.44 | P494: =IF('[1]Cleaned Text Field'!P494="",0,'[1]Cleaned Text Field'!P494) -> 0.25 | Q494: 4088.16 | R494: 3205.68 | S494: 882.48 | T494: =PROPER(TRIM([1]raw_orders!T494)) -> Paid | U494: =PROPER(TRIM([1]raw_orders!U494)) -> Completed | V494: =IF(Q494=0,0,S494/Q494) -> 0.21586239 | W494: =TEXT(B494,"mmmm") -> June | X494: =YEAR(B494) -> 2025 | Y494: =C494-B494 -> 4 | Z494: =P494 -> 0.25 | AA494: =N494*O494*(1-P494) -> 4088.16 | AB494: =Q494-R494 -> 882.48 | AC494: =IF(OR(B494="",C494="",AA494<=0),"Invalid",IF(Y494<0,"Warning",IF(Z494>100%,"Warning","Clean"))) -> Clean
A495: ORD-2025-10494 | B495: 45701 | C495: 45701 | D495: CUST-3765 | E495: =PROPER(TRIM([1]raw_orders!E495)) -> Kabir Singh | F495: =PROPER(TRIM([1]raw_orders!F495)) -> Corporate | G495: =IF('[1]Cleaned Text Field'!G495="","Unknown",'[1]Cleaned Text Field'!G495) -> East | H495: =PROPER(TRIM([1]raw_orders!H495)) -> Odisha | I495: =PROPER(TRIM([1]raw_orders!I495)) -> Bhubaneswar | J495: =PROPER(TRIM([1]raw_orders!J495)) -> Office Supplies | K495: =PROPER(TRIM([1]raw_orders!K495)) -> Paper | L495: Prime Paper 996 | M495: =IF('[1]Cleaned Text Field'!M495="","Unknown",'[1]Cleaned Text Field'!M495) -> Second Class | N495: =IF('[1]Cleaned Text Field'!N495="",0,'[1]Cleaned Text Field'!N495) -> 7 | O495: 2296.7 | P495: =IF('[1]Cleaned Text Field'!P495="",0,'[1]Cleaned Text Field'!P495) -> 0.05 | Q495: 15273.05 | R495: 11088.76 | S495: 4184.29 | T495: =PROPER(TRIM([1]raw_orders!T495)) -> Paid | U495: =PROPER(TRIM([1]raw_orders!U495)) -> Completed | V495: =IF(Q495=0,0,S495/Q495) -> 0.27396558 | W495: =TEXT(B495,"mmmm") -> February | X495: =YEAR(B495) -> 2025 | Y495: =C495-B495 -> 0 | Z495: =P495 -> 0.05 | AA495: =N495*O495*(1-P495) -> 15273.055 | AB495: =Q495-R495 -> 4184.29 | AC495: =IF(OR(B495="",C495="",AA495<=0),"Invalid",IF(Y495<0,"Warning",IF(Z495>100%,"Warning","Clean"))) -> Clean
... A501: ORD-2024-10500 | B501: 45648 | C501: 45652 | D501: CUST-5604 | E501: =PROPER(TRIM([1]raw_orders!E501)) -> Rahul Verma | F501: =PROPER(TRIM([1]raw_orders!F501)) -> Home Office | G501: =IF('[1]Cleaned Text Field'!G501="","Unknown",'[1]Cleaned Text Field'!G501) -> North | H501: =PROPER(TRIM([1]raw_orders!H501)) -> Uttar Pradesh | I501: =PROPER(TRIM([1]raw_orders!I501)) -> Noida | J501: =PROPER(TRIM([1]raw_orders!J501)) -> Furniture | K501: =PROPER(TRIM([1]raw_orders!K501)) -> Chairs | L501: Eco Chairs 210 | M501: =IF('[1]Cleaned Text Field'!M501="","Unknown",'[1]Cleaned Text Field'!M501) -> Standard Class | N501: =IF('[1]Cleaned Text Field'!N501="",0,'[1]Cleaned Text Field'!N501) -> 9 | O501: 1110.87 | P501: =IF('[1]Cleaned Text Field'!P501="",0,'[1]Cleaned Text Field'!P501) -> 0 | Q501: 7498.37 | R501: 6059.07 | S501: 1439.3 | T501: =PROPER(TRIM([1]raw_orders!T501)) -> Paid | U501: =PROPER(TRIM([1]raw_orders!U501)) -> Cancelled | V501: =IF(Q501=0,0,S501/Q501) -> 0.19194838 | W501: =TEXT(B501,"mmmm") -> December | X501: =YEAR(B501) -> 2024 | Y501: =C501-B501 -> 4 | Z501: =P501 -> 0 | AA501: =N501*O501*(1-P501) -> 9997.83 | AB501: =Q501-R501 -> 1439.3 | AC501: =IF(OR(B501="",C501="",AA501<=0),"Invalid",IF(Y501<0,"Warning",IF(Z501>100%,"Warning","Clean"))) -> Clean
A502: ORD-2024-10501 | B502: 45429 | C502: 45434 | D502: CUST-7661 | E502: =PROPER(TRIM([1]raw_orders!E502)) -> Sneha Kapoor | F502: =PROPER(TRIM([1]raw_orders!F502)) -> Consumer | G502: =IF('[1]Cleaned Text Field'!G502="","Unknown",'[1]Cleaned Text Field'!G502) -> South | H502: =PROPER(TRIM([1]raw_orders!H502)) -> Kerala | I502: =PROPER(TRIM([1]raw_orders!I502)) -> Kochi | J502: =PROPER(TRIM([1]raw_orders!J502)) -> Technology | K502: =PROPER(TRIM([1]raw_orders!K502)) -> Phones | L502: Prime Phones 533 | M502: =IF('[1]Cleaned Text Field'!M502="","Unknown",'[1]Cleaned Text Field'!M502) -> Same Day | N502: =IF('[1]Cleaned Text Field'!N502="",0,'[1]Cleaned Text Field'!N502) -> 9 | O502: 3795.99 | P502: =IF('[1]Cleaned Text Field'!P502="",0,'[1]Cleaned Text Field'!P502) -> 85% | Q502: 34163.91 | R502: 28577.15 | S502: 5586.76 | T502: =PROPER(TRIM([1]raw_orders!T502)) -> Paid | U502: =PROPER(TRIM([1]raw_orders!U502)) -> Completed | V502: =IF(Q502=0,0,S502/Q502) -> 0.16352812 | W502: =TEXT(B502,"mmmm") -> May | X502: =YEAR(B502) -> 2024 | Y502: =C502-B502 -> 5 | Z502: =VALUE(SUBSTITUTE(P502,"%",""))/100 -> 0.85 | AA502: =N502*O502*(1-P502) -> 5124.5865 | AB502: =Q502-R502 -> 5586.76 | AC502: =IF(OR(B502="",C502="",AA502<=0),"Invalid",IF(Y502<0,"Warning",IF(Z502>100%,"Warning","Clean"))) -> Clean
A503: ORD-2024-10502 | B503: 45515 | C503: 45521 | D503: CUST-3710 | E503: =PROPER(TRIM([1]raw_orders!E503)) -> Neha Gupta | F503: =PROPER(TRIM([1]raw_orders!F503)) -> Consumer | G503: =IF('[1]Cleaned Text Field'!G503="","Unknown",'[1]Cleaned Text Field'!G503) -> East | H503: =PROPER(TRIM([1]raw_orders!H503)) -> Jharkhand | I503: =PROPER(TRIM([1]raw_orders!I503)) -> Ranchi | J503: =PROPER(TRIM([1]raw_orders!J503)) -> Office Supplies | K503: =PROPER(TRIM([1]raw_orders!K503)) -> Art | L503: Elite Art 325 | M503: =IF('[1]Cleaned Text Field'!M503="","Unknown",'[1]Cleaned Text Field'!M503) -> Second Class | N503: =IF('[1]Cleaned Text Field'!N503="",0,'[1]Cleaned Text Field'!N503) -> 6 | O503: 3497.54 | P503: =IF('[1]Cleaned Text Field'!P503="",0,'[1]Cleaned Text Field'!P503) -> 0.15 | Q503: 17837.45 | R503: 13627.02 | S503: 4210.43 | T503: =PROPER(TRIM([1]raw_orders!T503)) -> Paid | U503: =PROPER(TRIM([1]raw_orders!U503)) -> Completed | V503: =IF(Q503=0,0,S503/Q503) -> 0.23604439 | W503: =TEXT(B503,"mmmm") -> August | X503: =YEAR(B503) -> 2024 | Y503: =C503-B503 -> 6 | Z503: =P503 -> 0.15 | AA503: =N503*O503*(1-P503) -> 17837.454 | AB503: =Q503-R503 -> 4210.43 | AC503: =IF(OR(B503="",C503="",AA503<=0),"Invalid",IF(Y503<0,"Warning",IF(Z503>100%,"Warning","Clean"))) -> Clean
A504: ORD-2024-10503 | B504: 45383 | C504: 45391 | D504: CUST-1534 | E504: =PROPER(TRIM([1]raw_orders!E504)) -> Priya Menon | F504: =PROPER(TRIM([1]raw_orders!F504)) -> Small Business | G504: =IF('[1]Cleaned Text Field'!G504="","Unknown",'[1]Cleaned Text Field'!G504) -> East | H504: =PROPER(TRIM([1]raw_orders!H504)) -> Odisha | I504: =PROPER(TRIM([1]raw_orders!I504)) -> Bhubaneswar | J504: =PROPER(TRIM([1]raw_orders!J504)) -> Technology | K504: =PROPER(TRIM([1]raw_orders!K504)) -> Copiers | L504: Prime Copiers 557 | M504: =IF('[1]Cleaned Text Field'!M504="","Unknown",'[1]Cleaned Text Field'!M504) -> Second Class | N504: =IF('[1]Cleaned Text Field'!N504="",0,'[1]Cleaned Text Field'!N504) -> 6 | O504: 826.93 | P504: =IF('[1]Cleaned Text Field'!P504="",0,'[1]Cleaned Text Field'!P504) -> 0.1 | Q504: 4465.42 | R504: 3377.1 | S504: 1088.32 | T504: =PROPER(TRIM([1]raw_orders!T504)) -> Paid | U504: =PROPER(TRIM([1]raw_orders!U504)) -> Completed | V504: =IF(Q504=0,0,S504/Q504) -> 0.24372176 | W504: =TEXT(B504,"mmmm") -> April | X504: =YEAR(B504) -> 2024 | Y504: =C504-B504 -> 8 | Z504: =P504 -> 0.1 | AA504: =N504*O504*(1-P504) -> 4465.422 | AB504: =Q504-R504 -> 1088.32 | AC504: =IF(OR(B504="",C504="",AA504<=0),"Invalid",IF(Y504<0,"Warning",IF(Z504>100%,"Warning","Clean"))) -> Clean
A505: ORD-2024-10504 | B505: 45563 | C505: 45570 | D505: CUST-7422 | E505: =PROPER(TRIM([1]raw_orders!E505)) -> Aarav Sharma | F505: =PROPER(TRIM([1]raw_orders!F505)) -> Consumer | G505: =IF('[1]Cleaned Text Field'!G505="","Unknown",'[1]Cleaned Text Field'!G505) -> South | H505: =PROPER(TRIM([1]raw_orders!H505)) -> Tamil Nadu | I505: =PROPER(TRIM([1]raw_orders!I505)) -> Chennai | J505: =PROPER(TRIM([1]raw_orders!J505)) -> Technology | K505: =PROPER(TRIM([1]raw_orders!K505)) -> Phones | L505: Smart Phones 674 | M505: =IF('[1]Cleaned Text Field'!M505="","Unknown",'[1]Cleaned Text Field'!M505) -> Standard Class | N505: =IF('[1]Cleaned Text Field'!N505="",0,'[1]Cleaned Text Field'!N505) -> 7 | O505: 1681.6 | P505: =IF('[1]Cleaned Text Field'!P505="",0,'[1]Cleaned Text Field'!P505) -> 0.1 | Q505: 10594.08 | R505: 7160.31 | S505: 3433.77 | T505: =PROPER(TRIM([1]raw_orders!T505)) -> Paid | U505: =PROPER(TRIM([1]raw_orders!U505)) -> Completed | V505: =IF(Q505=0,0,S505/Q505) -> 0.32412158 | W505: =TEXT(B505,"mmmm") -> September | X505: =YEAR(B505) -> 2024 | Y505: =C505-B505 -> 7 | Z505: =P505 -> 0.1 | AA505: =N505*O505*(1-P505) -> 10594.08 | AB505: =Q505-R505 -> 3433.77 | AC505: =IF(OR(B505="",C505="",AA505<=0),"Invalid",IF(Y505<0,"Warning",IF(Z505>100%,"Warning","Clean"))) -> Clean
A506: ORD-2025-10505 | B506: 45700 | C506: 45705 | D506: CUST-9693 | E506: =PROPER(TRIM([1]raw_orders!E506)) -> Arjun Bose | F506: =PROPER(TRIM([1]raw_orders!F506)) -> Corporate | G506: =IF('[1]Cleaned Text Field'!G506="","Unknown",'[1]Cleaned Text Field'!G506) -> West | H506: =PROPER(TRIM([1]raw_orders!H506)) -> Gujarat | I506: =PROPER(TRIM([1]raw_orders!I506)) -> Ahmedabad | J506: =PROPER(TRIM([1]raw_orders!J506)) -> Office Supplies | K506: =PROPER(TRIM([1]raw_orders!K506)) -> Art | L506: Elite Art 553 | M506: =IF('[1]Cleaned Text Field'!M506="","Unknown",'[1]Cleaned Text Field'!M506) -> Standard Class | N506: =IF('[1]Cleaned Text Field'!N506="",0,'[1]Cleaned Text Field'!N506) -> 4 | O506: 4328.12 | P506: =IF('[1]Cleaned Text Field'!P506="",0,'[1]Cleaned Text Field'!P506) -> 0 | Q506: 17312.48 | R506: 14424.22 | S506: 2888.26 | T506: =PROPER(TRIM([1]raw_orders!T506)) -> Paid | U506: =PROPER(TRIM([1]raw_orders!U506)) -> Completed | V506: =IF(Q506=0,0,S506/Q506) -> 0.1668311 | W506: =TEXT(B506,"mmmm") -> February | X506: =YEAR(B506) -> 2025 | Y506: =C506-B506 -> 5 | Z506: =P506 -> 0 | AA506: =N506*O506*(1-P506) -> 17312.48 | AB506: =Q506-R506 -> 2888.26 | AC506: =IF(OR(B506="",C506="",AA506<=0),"Invalid",IF(Y506<0,"Warning",IF(Z506>100%,"Warning","Clean"))) -> Clean
A507: ORD-2024-10506 | B507: 45605 | C507: 45610 | D507: CUST-5458 | E507: =PROPER(TRIM([1]raw_orders!E507)) -> Neha Gupta | F507: =PROPER(TRIM([1]raw_orders!F507)) -> Corporate | G507: =IF('[1]Cleaned Text Field'!G507="","Unknown",'[1]Cleaned Text Field'!G507) -> West | H507: =PROPER(TRIM([1]raw_orders!H507)) -> Madhya Pradesh | I507: =PROPER(TRIM([1]raw_orders!I507)) -> Indore | J507: =PROPER(TRIM([1]raw_orders!J507)) -> Office Supplies | K507: =PROPER(TRIM([1]raw_orders!K507)) -> Art | L507: Classic Art 339 | M507: =IF('[1]Cleaned Text Field'!M507="","Unknown",'[1]Cleaned Text Field'!M507) -> First Class | N507: =IF('[1]Cleaned Text Field'!N507="",0,'[1]Cleaned Text Field'!N507) -> 9 | O507: 2438.29 | P507: =IF('[1]Cleaned Text Field'!P507="",0,'[1]Cleaned Text Field'!P507) -> 0.2 | Q507: 17555.69 | R507: 13293.2 | S507: 4262.49 | T507: =PROPER(TRIM([1]raw_orders!T507)) -> Paid | U507: =PROPER(TRIM([1]raw_orders!U507)) -> Cancelled | V507: =IF(Q507=0,0,S507/Q507) -> 0.2427982 | W507: =TEXT(B507,"mmmm") -> November | X507: =YEAR(B507) -> 2024 | Y507: =C507-B507 -> 5 | Z507: =P507 -> 0.2 | AA507: =N507*O507*(1-P507) -> 17555.688 | AB507: =Q507-R507 -> 4262.49 | AC507: =IF(OR(B507="",C507="",AA507<=0),"Invalid",IF(Y507<0,"Warning",IF(Z507>100%,"Warning","Clean"))) -> Clean
A508: ORD-2024-10507 | B508: 45641 | C508: 45641 | D508: CUST-3011 | E508: =PROPER(TRIM([1]raw_orders!E508)) -> Aarav Sharma | F508: =PROPER(TRIM([1]raw_orders!F508)) -> Small Business | G508: =IF('[1]Cleaned Text Field'!G508="","Unknown",'[1]Cleaned Text Field'!G508) -> North | H508: =PROPER(TRIM([1]raw_orders!H508)) -> Punjab | I508: =PROPER(TRIM([1]raw_orders!I508)) -> Ludhiana | J508: =PROPER(TRIM([1]raw_orders!J508)) -> Furniture | K508: =PROPER(TRIM([1]raw_orders!K508)) -> Furnishings | L508: Smart Furnishings 352 | M508: =IF('[1]Cleaned Text Field'!M508="","Unknown",'[1]Cleaned Text Field'!M508) -> First Class | N508: =IF('[1]Cleaned Text Field'!N508="",0,'[1]Cleaned Text Field'!N508) -> 2 | O508: 669.8 | P508: =IF('[1]Cleaned Text Field'!P508="",0,'[1]Cleaned Text Field'!P508) -> 0.1 | Q508: 1205.64 | R508: 842.07 | S508: 363.57 | T508: =PROPER(TRIM([1]raw_orders!T508)) -> Refunded | U508: =PROPER(TRIM([1]raw_orders!U508)) -> Returned | V508: =IF(Q508=0,0,S508/Q508) -> 0.30155768 | W508: =TEXT(B508,"mmmm") -> December | X508: =YEAR(B508) -> 2024 | Y508: =C508-B508 -> 0 | Z508: =P508 -> 0.1 | AA508: =N508*O508*(1-P508) -> 1205.64 | AB508: =Q508-R508 -> 363.57 | AC508: =IF(OR(B508="",C508="",AA508<=0),"Invalid",IF(Y508<0,"Warning",IF(Z508>100%,"Warning","Clean"))) -> Clean
A509: ORD-2025-10508 | B509: 45762 | C509: 45769 | D509: CUST-1826 | E509: =PROPER(TRIM([1]raw_orders!E509)) -> Isha Nair | F509: =PROPER(TRIM([1]raw_orders!F509)) -> Small Business | G509: =IF('[1]Cleaned Text Field'!G509="","Unknown",'[1]Cleaned Text Field'!G509) -> North | H509: =PROPER(TRIM([1]raw_orders!H509)) -> Haryana | I509: =PROPER(TRIM([1]raw_orders!I509)) -> Gurugram | J509: =PROPER(TRIM([1]raw_orders!J509)) -> Office Supplies | K509: =PROPER(TRIM([1]raw_orders!K509)) -> Binders | L509: Classic Binders 602 | M509: =IF('[1]Cleaned Text Field'!M509="","Unknown",'[1]Cleaned Text Field'!M509) -> Same Day | N509: =IF('[1]Cleaned Text Field'!N509="",0,'[1]Cleaned Text Field'!N509) -> 4 | O509: 2990.42 | P509: =IF('[1]Cleaned Text Field'!P509="",0,'[1]Cleaned Text Field'!P509) -> 0.25 | Q509: 8971.26 | R509: 6814.35 | S509: 2156.91 | T509: =PROPER(TRIM([1]raw_orders!T509)) -> Paid | U509: =PROPER(TRIM([1]raw_orders!U509)) -> Completed | V509: =IF(Q509=0,0,S509/Q509) -> 0.24042442 | W509: =TEXT(B509,"mmmm") -> April | X509: =YEAR(B509) -> 2025 | Y509: =C509-B509 -> 7 | Z509: =P509 -> 0.25 | AA509: =N509*O509*(1-P509) -> 8971.26 | AB509: =Q509-R509 -> 2156.91 | AC509: =IF(OR(B509="",C509="",AA509<=0),"Invalid",IF(Y509<0,"Warning",IF(Z509>100%,"Warning","Clean"))) -> Clean
A510: ORD-2024-10509 | B510: 45382 | C510: 45477 | D510: CUST-3333 | E510: =PROPER(TRIM([1]raw_orders!E510)) -> Isha Nair | F510: =PROPER(TRIM([1]raw_orders!F510)) -> Small Business | G510: =IF('[1]Cleaned Text Field'!G510="","Unknown",'[1]Cleaned Text Field'!G510) -> North | H510: =PROPER(TRIM([1]raw_orders!H510)) -> Haryana | I510: =PROPER(TRIM([1]raw_orders!I510)) -> Gurugram | J510: =PROPER(TRIM([1]raw_orders!J510)) -> Technology | K510: =PROPER(TRIM([1]raw_orders!K510)) -> Machines | L510: Smart Machines 853 | M510: =IF('[1]Cleaned Text Field'!M510="","Unknown",'[1]Cleaned Text Field'!M510) -> Second Class | N510: =IF('[1]Cleaned Text Field'!N510="",0,'[1]Cleaned Text Field'!N510) -> 4 | O510: 1831 | P510: =IF('[1]Cleaned Text Field'!P510="",0,'[1]Cleaned Text Field'!P510) -> 0 | Q510: 7324 | R510: 4179.63 | S510: 3144.37 | T510: =PROPER(TRIM([1]raw_orders!T510)) -> Paid | U510: =PROPER(TRIM([1]raw_orders!U510)) -> Completed | V510: =IF(Q510=0,0,S510/Q510) -> 0.42932414 | W510: =TEXT(B510,"mmmm") -> March | X510: =YEAR(B510) -> 2024 | Y510: =C510-B510 -> 95 | Z510: =P510 -> 0 | AA510: =N510*O510*(1-P510) -> 7324 | AB510: =Q510-R510 -> 3144.37 | AC510: =IF(OR(B510="",C510="",AA510<=0),"Invalid",IF(Y510<0,"Warning",IF(Z510>100%,"Warning","Clean"))) -> Clean
A511: ORD-2025-10510 | B511: 45789 | C511: 45791 | D511: CUST-7901 | E511: =PROPER(TRIM([1]raw_orders!E511)) -> Neha Gupta | F511: =PROPER(TRIM([1]raw_orders!F511)) -> Consumer | G511: =IF('[1]Cleaned Text Field'!G511="","Unknown",'[1]Cleaned Text Field'!G511) -> West | H511: =PROPER(TRIM([1]raw_orders!H511)) -> Gujarat | I511: =PROPER(TRIM([1]raw_orders!I511)) -> Ahmedabad | J511: =PROPER(TRIM([1]raw_orders!J511)) -> Technology | K511: =PROPER(TRIM([1]raw_orders!K511)) -> Machines | L511: Classic Machines 599 | M511: =IF('[1]Cleaned Text Field'!M511="","Unknown",'[1]Cleaned Text Field'!M511) -> Same Day | N511: =IF('[1]Cleaned Text Field'!N511="",0,'[1]Cleaned Text Field'!N511) -> 8 | O511: 3631.44 | P511: =IF('[1]Cleaned Text Field'!P511="",0,'[1]Cleaned Text Field'!P511) -> 0.2 | Q511: 23241.22 | R511: 17220.9 | S511: 6020.32 | T511: =PROPER(TRIM([1]raw_orders!T511)) -> Paid | U511: =PROPER(TRIM([1]raw_orders!U511)) -> Completed | V511: =IF(Q511=0,0,S511/Q511) -> 0.25903632 | W511: =TEXT(B511,"mmmm") -> May | X511: =YEAR(B511) -> 2025 | Y511: =C511-B511 -> 2 | Z511: =P511 -> 0.2 | AA511: =N511*O511*(1-P511) -> 23241.216 | AB511: =Q511-R511 -> 6020.32 | AC511: =IF(OR(B511="",C511="",AA511<=0),"Invalid",IF(Y511<0,"Warning",IF(Z511>100%,"Warning","Clean"))) -> Clean
A512: ORD-2024-10511 | B512: 45583 | C512: 45586 | D512: CUST-9759 | E512: =PROPER(TRIM([1]raw_orders!E512)) -> Aarav Sharma | F512: =PROPER(TRIM([1]raw_orders!F512)) -> Consumer | G512: =IF('[1]Cleaned Text Field'!G512="","Unknown",'[1]Cleaned Text Field'!G512) -> South | H512: =PROPER(TRIM([1]raw_orders!H512)) -> Karnataka | I512: =PROPER(TRIM([1]raw_orders!I512)) -> Bengaluru | J512: =PROPER(TRIM([1]raw_orders!J512)) -> Office Supplies | K512: =PROPER(TRIM([1]raw_orders!K512)) -> Storage | L512: Pro Storage 373 | M512: =IF('[1]Cleaned Text Field'!M512="","Unknown",'[1]Cleaned Text Field'!M512) -> Second Class | N512: =IF('[1]Cleaned Text Field'!N512="",0,'[1]Cleaned Text Field'!N512) -> 2 | O512: 4238.51 | P512: =IF('[1]Cleaned Text Field'!P512="",0,'[1]Cleaned Text Field'!P512) -> 0 | Q512: 8477.02 | R512: 6884.96 | S512: 1592.06 | T512: =PROPER(TRIM([1]raw_orders!T512)) -> Paid | U512: =PROPER(TRIM([1]raw_orders!U512)) -> Completed | V512: =IF(Q512=0,0,S512/Q512) -> 0.18780892 | W512: =TEXT(B512,"mmmm") -> October | X512: =YEAR(B512) -> 2024 | Y512: =C512-B512 -> 3 | Z512: =P512 -> 0 | AA512: =N512*O512*(1-P512) -> 8477.02 | AB512: =Q512-R512 -> 1592.06 | AC512: =IF(OR(B512="",C512="",AA512<=0),"Invalid",IF(Y512<0,"Warning",IF(Z512>100%,"Warning","Clean"))) -> Clean
A513: ORD-2024-10512 | B513: 45588 | C513: 45591 | D513: CUST-7232 | E513: =PROPER(TRIM([1]raw_orders!E513)) -> Sneha Kapoor | F513: =PROPER(TRIM([1]raw_orders!F513)) -> Consumer | G513: =IF('[1]Cleaned Text Field'!G513="","Unknown",'[1]Cleaned Text Field'!G513) -> West | H513: =PROPER(TRIM([1]raw_orders!H513)) -> Madhya Pradesh | I513: =PROPER(TRIM([1]raw_orders!I513)) -> Indore | J513: =PROPER(TRIM([1]raw_orders!J513)) -> Furniture | K513: =PROPER(TRIM([1]raw_orders!K513)) -> Bookcases | L513: Smart Bookcases 920 | M513: =IF('[1]Cleaned Text Field'!M513="","Unknown",'[1]Cleaned Text Field'!M513) -> Standard Class | N513: =IF('[1]Cleaned Text Field'!N513="",0,'[1]Cleaned Text Field'!N513) -> 9 | O513: 544.27 | P513: =IF('[1]Cleaned Text Field'!P513="",0,'[1]Cleaned Text Field'!P513) -> 0.25 | Q513: 3673.82 | R513: 2088.15 | S513: 1585.67 | T513: =PROPER(TRIM([1]raw_orders!T513)) -> Paid | U513: =PROPER(TRIM([1]raw_orders!U513)) -> Completed | V513: =IF(Q513=0,0,S513/Q513) -> 0.43161342 | W513: =TEXT(B513,"mmmm") -> October | X513: =YEAR(B513) -> 2024 | Y513: =C513-B513 -> 3 | Z513: =P513 -> 0.25 | AA513: =N513*O513*(1-P513) -> 3673.8225 | AB513: =Q513-R513 -> 1585.67 | AC513: =IF(OR(B513="",C513="",AA513<=0),"Invalid",IF(Y513<0,"Warning",IF(Z513>100%,"Warning","Clean"))) -> Clean
A514: ORD-2025-10513 | B514: 45718 | C514: 45719 | D514: CUST-9943 | E514: =PROPER(TRIM([1]raw_orders!E514)) -> Isha Nair | F514: =PROPER(TRIM([1]raw_orders!F514)) -> Corporate | G514: =IF('[1]Cleaned Text Field'!G514="","Unknown",'[1]Cleaned Text Field'!G514) -> South | H514: =PROPER(TRIM([1]raw_orders!H514)) -> Kerala | I514: =PROPER(TRIM([1]raw_orders!I514)) -> Kochi | J514: =PROPER(TRIM([1]raw_orders!J514)) -> Office Supplies | K514: =PROPER(TRIM([1]raw_orders!K514)) -> Labels | L514: Pro Labels 849 | M514: =IF('[1]Cleaned Text Field'!M514="","Unknown",'[1]Cleaned Text Field'!M514) -> Second Class | N514: =IF('[1]Cleaned Text Field'!N514="",0,'[1]Cleaned Text Field'!N514) -> 2 | O514: 4031.45 | P514: =IF('[1]Cleaned Text Field'!P514="",0,'[1]Cleaned Text Field'!P514) -> 0.25 | Q514: 6047.17 | R514: 3368.79 | S514: 2678.38 | T514: =PROPER(TRIM([1]raw_orders!T514)) -> Paid | U514: =PROPER(TRIM([1]raw_orders!U514)) -> Completed | V514: =IF(Q514=0,0,S514/Q514) -> 0.44291462 | W514: =TEXT(B514,"mmmm") -> March | X514: =YEAR(B514) -> 2025 | Y514: =C514-B514 -> 1 | Z514: =P514 -> 0.25 | AA514: =N514*O514*(1-P514) -> 6047.175 | AB514: =Q514-R514 -> 2678.38 | AC514: =IF(OR(B514="",C514="",AA514<=0),"Invalid",IF(Y514<0,"Warning",IF(Z514>100%,"Warning","Clean"))) -> Clean
... A553: ORD-2024-10552 | B553: 45349 | C553: 45349 | D553: CUST-8172 | E553: =PROPER(TRIM([1]raw_orders!E553)) -> Sneha Kapoor | F553: =PROPER(TRIM([1]raw_orders!F553)) -> Consumer | G553: =IF('[1]Cleaned Text Field'!G553="","Unknown",'[1]Cleaned Text Field'!G553) -> East | H553: =PROPER(TRIM([1]raw_orders!H553)) -> Jharkhand | I553: =PROPER(TRIM([1]raw_orders!I553)) -> Ranchi | J553: =PROPER(TRIM([1]raw_orders!J553)) -> Furniture | K553: =PROPER(TRIM([1]raw_orders!K553)) -> Chairs | L553: Elite Chairs 314 | M553: =IF('[1]Cleaned Text Field'!M553="","Unknown",'[1]Cleaned Text Field'!M553) -> Second Class | N553: =IF('[1]Cleaned Text Field'!N553="",0,'[1]Cleaned Text Field'!N553) -> 3 | O553: 3148.09 | P553: =IF('[1]Cleaned Text Field'!P553="",0,'[1]Cleaned Text Field'!P553) -> 0.15 | Q553: 8027.63 | R553: 5496.09 | S553: 2531.54 | T553: =PROPER(TRIM([1]raw_orders!T553)) -> Paid | U553: =PROPER(TRIM([1]raw_orders!U553)) -> Completed | V553: =IF(Q553=0,0,S553/Q553) -> 0.31535335 | W553: =TEXT(B553,"mmmm") -> February | X553: =YEAR(B553) -> 2024 | Y553: =C553-B553 -> 0 | Z553: =P553 -> 0.15 | AA553: =N553*O553*(1-P553) -> 8027.6295 | AB553: =Q553-R553 -> 2531.54 | AC553: =IF(OR(B553="",C553="",AA553<=0),"Invalid",IF(Y553<0,"Warning",IF(Z553>100%,"Warning","Clean"))) -> Clean
A554: ORD-2025-10553 | B554: 45681 | C554: 45687 | D554: CUST-8861 | E554: =PROPER(TRIM([1]raw_orders!E554)) -> Ananya Rao | F554: =PROPER(TRIM([1]raw_orders!F554)) -> Corporate | G554: =IF('[1]Cleaned Text Field'!G554="","Unknown",'[1]Cleaned Text Field'!G554) -> East | H554: =PROPER(TRIM([1]raw_orders!H554)) -> West Bengal | I554: =PROPER(TRIM([1]raw_orders!I554)) -> Kolkata | J554: =PROPER(TRIM([1]raw_orders!J554)) -> Technology | K554: =PROPER(TRIM([1]raw_orders!K554)) -> Copiers | L554: Pro Copiers 246 | M554: =IF('[1]Cleaned Text Field'!M554="","Unknown",'[1]Cleaned Text Field'!M554) -> Standard Class | N554: =IF('[1]Cleaned Text Field'!N554="",0,'[1]Cleaned Text Field'!N554) -> 8 | O554: 312.53 | P554: =IF('[1]Cleaned Text Field'!P554="",0,'[1]Cleaned Text Field'!P554) -> 70% | Q554: 1875.18 | R554: 1579.17 | S554: 296.01 | T554: =PROPER(TRIM([1]raw_orders!T554)) -> Paid | U554: =PROPER(TRIM([1]raw_orders!U554)) -> Completed | V554: =IF(Q554=0,0,S554/Q554) -> 0.15785685 | W554: =TEXT(B554,"mmmm") -> January | X554: =YEAR(B554) -> 2025 | Y554: =C554-B554 -> 6 | Z554: =VALUE(SUBSTITUTE(P554,"%",""))/100 -> 0.7 | AA554: =N554*O554*(1-P554) -> 750.072 | AB554: =Q554-R554 -> 296.01 | AC554: =IF(OR(B554="",C554="",AA554<=0),"Invalid",IF(Y554<0,"Warning",IF(Z554>100%,"Warning","Clean"))) -> Clean
A555: ORD-2025-10554 | B555: 45772 | C555: 45775 | D555: CUST-9241 | E555: =PROPER(TRIM([1]raw_orders!E555)) -> Aarav Sharma | F555: =PROPER(TRIM([1]raw_orders!F555)) -> Small Business | G555: =IF('[1]Cleaned Text Field'!G555="","Unknown",'[1]Cleaned Text Field'!G555) -> West | H555: =PROPER(TRIM([1]raw_orders!H555)) -> Gujarat | I555: =PROPER(TRIM([1]raw_orders!I555)) -> Ahmedabad | J555: =PROPER(TRIM([1]raw_orders!J555)) -> Office Supplies | K555: =PROPER(TRIM([1]raw_orders!K555)) -> Storage | L555: Pro Storage 128 | M555: =IF('[1]Cleaned Text Field'!M555="","Unknown",'[1]Cleaned Text Field'!M555) -> First Class | N555: =IF('[1]Cleaned Text Field'!N555="",0,'[1]Cleaned Text Field'!N555) -> 9 | O555: 1294.11 | P555: =IF('[1]Cleaned Text Field'!P555="",0,'[1]Cleaned Text Field'!P555) -> 0.25 | Q555: 8735.24 | R555: 6620.07 | S555: 2115.17 | T555: =PROPER(TRIM([1]raw_orders!T555)) -> Paid | U555: =PROPER(TRIM([1]raw_orders!U555)) -> Completed | V555: =IF(Q555=0,0,S555/Q555) -> 0.24214217 | W555: =TEXT(B555,"mmmm") -> April | X555: =YEAR(B555) -> 2025 | Y555: =C555-B555 -> 3 | Z555: =P555 -> 0.25 | AA555: =N555*O555*(1-P555) -> 8735.2425 | AB555: =Q555-R555 -> 2115.17 | AC555: =IF(OR(B555="",C555="",AA555<=0),"Invalid",IF(Y555<0,"Warning",IF(Z555>100%,"Warning","Clean"))) -> Clean
A556: ORD-2024-10555 | B556: 45577 | C556: 45582 | D556: CUST-2126 | E556: =PROPER(TRIM([1]raw_orders!E556)) -> Arjun Bose | F556: =PROPER(TRIM([1]raw_orders!F556)) -> Consumer | G556: =IF('[1]Cleaned Text Field'!G556="","Unknown",'[1]Cleaned Text Field'!G556) -> Unknown | H556: =PROPER(TRIM([1]raw_orders!H556)) -> Jharkhand | I556: =PROPER(TRIM([1]raw_orders!I556)) -> Ranchi | J556: =PROPER(TRIM([1]raw_orders!J556)) -> Furniture | K556: =PROPER(TRIM([1]raw_orders!K556)) -> Furnishings | L556: Prime Furnishings 892 | M556: =IF('[1]Cleaned Text Field'!M556="","Unknown",'[1]Cleaned Text Field'!M556) -> Standard Class | N556: =IF('[1]Cleaned Text Field'!N556="",0,'[1]Cleaned Text Field'!N556) -> 4 | O556: 1071.22 | P556: =IF('[1]Cleaned Text Field'!P556="",0,'[1]Cleaned Text Field'!P556) -> 0.05 | Q556: 4070.64 | R556: 2831.62 | S556: 1239.02 | T556: =PROPER(TRIM([1]raw_orders!T556)) -> Paid | U556: =PROPER(TRIM([1]raw_orders!U556)) -> Completed | V556: =IF(Q556=0,0,S556/Q556) -> 0.30437966 | W556: =TEXT(B556,"mmmm") -> October | X556: =YEAR(B556) -> 2024 | Y556: =C556-B556 -> 5 | Z556: =P556 -> 0.05 | AA556: =N556*O556*(1-P556) -> 4070.636 | AB556: =Q556-R556 -> 1239.02 | AC556: =IF(OR(B556="",C556="",AA556<=0),"Invalid",IF(Y556<0,"Warning",IF(Z556>100%,"Warning","Clean"))) -> Clean
A557: ORD-2025-10556 | B557: 45749 | C557: 45698 | D557: CUST-7513 | E557: =PROPER(TRIM([1]raw_orders!E557)) -> Ananya Rao | F557: =PROPER(TRIM([1]raw_orders!F557)) -> Small Business | G557: =IF('[1]Cleaned Text Field'!G557="","Unknown",'[1]Cleaned Text Field'!G557) -> South | H557: =PROPER(TRIM([1]raw_orders!H557)) -> Telangana | I557: =PROPER(TRIM([1]raw_orders!I557)) -> Hyderabad | J557: =PROPER(TRIM([1]raw_orders!J557)) -> Office Supplies | K557: =PROPER(TRIM([1]raw_orders!K557)) -> Storage | L557: Prime Storage 689 | M557: =IF('[1]Cleaned Text Field'!M557="","Unknown",'[1]Cleaned Text Field'!M557) -> Standard Class | N557: =IF('[1]Cleaned Text Field'!N557="",0,'[1]Cleaned Text Field'!N557) -> 6 | O557: 1042.8 | P557: =IF('[1]Cleaned Text Field'!P557="",0,'[1]Cleaned Text Field'!P557) -> 0.05 | Q557: 5943.96 | R557: 3604.14 | S557: 2339.82 | T557: =PROPER(TRIM([1]raw_orders!T557)) -> Paid | U557: =PROPER(TRIM([1]raw_orders!U557)) -> Completed | V557: =IF(Q557=0,0,S557/Q557) -> 0.39364666 | W557: =TEXT(B557,"mmmm") -> April | X557: =YEAR(B557) -> 2025 | Y557: =C557-B557 -> -51 | Z557: =P557 -> 0.05 | AA557: =N557*O557*(1-P557) -> 5943.96 | AB557: =Q557-R557 -> 2339.82 | AC557: =IF(OR(B557="",C557="",AA557<=0),"Invalid",IF(Y557<0,"Warning",IF(Z557>100%,"Warning","Clean"))) -> Warning
A558: ORD-2024-10557 | B558: 45466 | C558: 45472 | D558: CUST-1992 | E558: =PROPER(TRIM([1]raw_orders!E558)) -> Neha Gupta | F558: =PROPER(TRIM([1]raw_orders!F558)) -> Consumer | G558: =IF('[1]Cleaned Text Field'!G558="","Unknown",'[1]Cleaned Text Field'!G558) -> North | H558: =PROPER(TRIM([1]raw_orders!H558)) -> Haryana | I558: =PROPER(TRIM([1]raw_orders!I558)) -> Gurugram | J558: =PROPER(TRIM([1]raw_orders!J558)) -> Furniture | K558: =PROPER(TRIM([1]raw_orders!K558)) -> Tables | L558: Classic Tables 769 | M558: =IF('[1]Cleaned Text Field'!M558="","Unknown",'[1]Cleaned Text Field'!M558) -> First Class | N558: =IF('[1]Cleaned Text Field'!N558="",0,'[1]Cleaned Text Field'!N558) -> 1 | O558: 4426.66 | P558: =IF('[1]Cleaned Text Field'!P558="",0,'[1]Cleaned Text Field'!P558) -> 0 | Q558: 4426.66 | R558: 3035.2 | S558: 1816.23 | T558: =PROPER(TRIM([1]raw_orders!T558)) -> Paid | U558: =PROPER(TRIM([1]raw_orders!U558)) -> Returned | V558: =IF(Q558=0,0,S558/Q558) -> 0.41029354 | W558: =TEXT(B558,"mmmm") -> June | X558: =YEAR(B558) -> 2024 | Y558: =C558-B558 -> 6 | Z558: =P558 -> 0 | AA558: =N558*O558*(1-P558) -> 4426.66 | AB558: =Q558-R558 -> 1391.46 | AC558: =IF(OR(B558="",C558="",AA558<=0),"Invalid",IF(Y558<0,"Warning",IF(Z558>100%,"Warning","Clean"))) -> Clean
A559: ORD-2024-10558 | B559: 45420 | C559: 45426 | D559: CUST-8848 | E559: =PROPER(TRIM([1]raw_orders!E559)) -> Vikram Iyer | F559: =PROPER(TRIM([1]raw_orders!F559)) -> Home Office | G559: =IF('[1]Cleaned Text Field'!G559="","Unknown",'[1]Cleaned Text Field'!G559) -> North | H559: =PROPER(TRIM([1]raw_orders!H559)) -> Haryana | I559: =PROPER(TRIM([1]raw_orders!I559)) -> Gurugram | J559: =PROPER(TRIM([1]raw_orders!J559)) -> Technology | K559: =PROPER(TRIM([1]raw_orders!K559)) -> Phones | L559: Prime Phones 503 | M559: =IF('[1]Cleaned Text Field'!M559="","Unknown",'[1]Cleaned Text Field'!M559) -> First Class | N559: =IF('[1]Cleaned Text Field'!N559="",0,'[1]Cleaned Text Field'!N559) -> 9 | O559: 3769.46 | P559: =IF('[1]Cleaned Text Field'!P559="",0,'[1]Cleaned Text Field'!P559) -> 0.05 | Q559: 32228.88 | R559: 24971.36 | S559: 7257.52 | T559: =PROPER(TRIM([1]raw_orders!T559)) -> Paid | U559: =PROPER(TRIM([1]raw_orders!U559)) -> Cancelled | V559: =IF(Q559=0,0,S559/Q559) -> 0.22518685 | W559: =TEXT(B559,"mmmm") -> May | X559: =YEAR(B559) -> 2024 | Y559: =C559-B559 -> 6 | Z559: =P559 -> 0.05 | AA559: =N559*O559*(1-P559) -> 32228.883 | AB559: =Q559-R559 -> 7257.52 | AC559: =IF(OR(B559="",C559="",AA559<=0),"Invalid",IF(Y559<0,"Warning",IF(Z559>100%,"Warning","Clean"))) -> Clean
A560: ORD-2025-10559 | B560: 45904 | C560: 45904 | D560: CUST-9368 | E560: =PROPER(TRIM([1]raw_orders!E560)) -> Aditi Sen | F560: =PROPER(TRIM([1]raw_orders!F560)) -> Corporate | G560: =IF('[1]Cleaned Text Field'!G560="","Unknown",'[1]Cleaned Text Field'!G560) -> North | H560: =PROPER(TRIM([1]raw_orders!H560)) -> Punjab | I560: =PROPER(TRIM([1]raw_orders!I560)) -> Ludhiana | J560: =PROPER(TRIM([1]raw_orders!J560)) -> Technology | K560: =PROPER(TRIM([1]raw_orders!K560)) -> Machines | L560: Basic Machines 136 | M560: =IF('[1]Cleaned Text Field'!M560="","Unknown",'[1]Cleaned Text Field'!M560) -> First Class | N560: =IF('[1]Cleaned Text Field'!N560="",0,'[1]Cleaned Text Field'!N560) -> 8 | O560: 3079.95 | P560: =IF('[1]Cleaned Text Field'!P560="",0,'[1]Cleaned Text Field'!P560) -> 0.2 | Q560: 19711.68 | R560: 14461.8 | S560: 5249.88 | T560: =PROPER(TRIM([1]raw_orders!T560)) -> Paid | U560: =PROPER(TRIM([1]raw_orders!U560)) -> Completed | V560: =IF(Q560=0,0,S560/Q560) -> 0.26633346 | W560: =TEXT(B560,"mmmm") -> September | X560: =YEAR(B560) -> 2025 | Y560: =C560-B560 -> 0 | Z560: =P560 -> 0.2 | AA560: =N560*O560*(1-P560) -> 19711.68 | AB560: =Q560-R560 -> 5249.88 | AC560: =IF(OR(B560="",C560="",AA560<=0),"Invalid",IF(Y560<0,"Warning",IF(Z560>100%,"Warning","Clean"))) -> Clean
A561: ORD-2025-10560 | B561: 45930 | C561: 45937 | D561: CUST-6797 | E561: =PROPER(TRIM([1]raw_orders!E561)) -> Diya Patel | F561: =PROPER(TRIM([1]raw_orders!F561)) -> Corporate | G561: =IF('[1]Cleaned Text Field'!G561="","Unknown",'[1]Cleaned Text Field'!G561) -> East | H561: =PROPER(TRIM([1]raw_orders!H561)) -> Bihar | I561: =PROPER(TRIM([1]raw_orders!I561)) -> Patna | J561: =PROPER(TRIM([1]raw_orders!J561)) -> Technology | K561: =PROPER(TRIM([1]raw_orders!K561)) -> Copiers | L561: Basic Copiers 512 | M561: =IF('[1]Cleaned Text Field'!M561="","Unknown",'[1]Cleaned Text Field'!M561) -> Second Class | N561: =IF('[1]Cleaned Text Field'!N561="",0,'[1]Cleaned Text Field'!N561) -> 5 | O561: 3277.82 | P561: =IF('[1]Cleaned Text Field'!P561="",0,'[1]Cleaned Text Field'!P561) -> 0.1 | Q561: 14750.19 | R561: 9482.58 | S561: 5267.61 | T561: =PROPER(TRIM([1]raw_orders!T561)) -> Paid | U561: =PROPER(TRIM([1]raw_orders!U561)) -> Returned | V561: =IF(Q561=0,0,S561/Q561) -> 0.3571215 | W561: =TEXT(B561,"mmmm") -> September | X561: =YEAR(B561) -> 2025 | Y561: =C561-B561 -> 7 | Z561: =P561 -> 0.1 | AA561: =N561*O561*(1-P561) -> 14750.19 | AB561: =Q561-R561 -> 5267.61 | AC561: =IF(OR(B561="",C561="",AA561<=0),"Invalid",IF(Y561<0,"Warning",IF(Z561>100%,"Warning","Clean"))) -> Clean
A562: ORD-2024-10561 | B562: 45307 | C562: 45313 | D562: CUST-9333 | E562: =PROPER(TRIM([1]raw_orders!E562)) -> Arjun Bose | F562: =PROPER(TRIM([1]raw_orders!F562)) -> Consumer | G562: =IF('[1]Cleaned Text Field'!G562="","Unknown",'[1]Cleaned Text Field'!G562) -> West | H562: =PROPER(TRIM([1]raw_orders!H562)) -> Goa | I562: =PROPER(TRIM([1]raw_orders!I562)) -> Panaji | J562: =PROPER(TRIM([1]raw_orders!J562)) -> Office Supplies | K562: =PROPER(TRIM([1]raw_orders!K562)) -> Storage | L562: Smart Storage 767 | M562: =IF('[1]Cleaned Text Field'!M562="","Unknown",'[1]Cleaned Text Field'!M562) -> Standard Class | N562: =IF('[1]Cleaned Text Field'!N562="",0,'[1]Cleaned Text Field'!N562) -> 4 | O562: 282.53 | P562: =IF('[1]Cleaned Text Field'!P562="",0,'[1]Cleaned Text Field'!P562) -> 0 | Q562: 1130.12 | R562: 848.62 | S562: 281.5 | T562: =PROPER(TRIM([1]raw_orders!T562)) -> Paid | U562: =PROPER(TRIM([1]raw_orders!U562)) -> Cancelled | V562: =IF(Q562=0,0,S562/Q562) -> 0.24908859 | W562: =TEXT(B562,"mmmm") -> January | X562: =YEAR(B562) -> 2024 | Y562: =C562-B562 -> 6 | Z562: =P562 -> 0 | AA562: =N562*O562*(1-P562) -> 1130.12 | AB562: =Q562-R562 -> 281.5 | AC562: =IF(OR(B562="",C562="",AA562<=0),"Invalid",IF(Y562<0,"Warning",IF(Z562>100%,"Warning","Clean"))) -> Clean
A563: ORD-2025-10562 | B563: 45852 | C563: 45856 | D563: CUST-6654 | E563: =PROPER(TRIM([1]raw_orders!E563)) -> Aditi Sen | F563: =PROPER(TRIM([1]raw_orders!F563)) -> Consumer | G563: =IF('[1]Cleaned Text Field'!G563="","Unknown",'[1]Cleaned Text Field'!G563) -> North | H563: =PROPER(TRIM([1]raw_orders!H563)) -> Punjab | I563: =PROPER(TRIM([1]raw_orders!I563)) -> Ludhiana | J563: =PROPER(TRIM([1]raw_orders!J563)) -> Technology | K563: =PROPER(TRIM([1]raw_orders!K563)) -> Copiers | L563: Eco Copiers 954 | M563: =IF('[1]Cleaned Text Field'!M563="","Unknown",'[1]Cleaned Text Field'!M563) -> First Class | N563: =IF('[1]Cleaned Text Field'!N563="",0,'[1]Cleaned Text Field'!N563) -> 4 | O563: 725.22 | P563: =IF('[1]Cleaned Text Field'!P563="",0,'[1]Cleaned Text Field'!P563) -> 0 | Q563: 2900.88 | R563: 2391.85 | S563: 509.03 | T563: =PROPER(TRIM([1]raw_orders!T563)) -> Pending | U563: =PROPER(TRIM([1]raw_orders!U563)) -> Returned | V563: =IF(Q563=0,0,S563/Q563) -> 0.17547434 | W563: =TEXT(B563,"mmmm") -> July | X563: =YEAR(B563) -> 2025 | Y563: =C563-B563 -> 4 | Z563: =P563 -> 0 | AA563: =N563*O563*(1-P563) -> 2900.88 | AB563: =Q563-R563 -> 509.03 | AC563: =IF(OR(B563="",C563="",AA563<=0),"Invalid",IF(Y563<0,"Warning",IF(Z563>100%,"Warning","Clean"))) -> Clean
A564: ORD-2024-10563 | B564: 45422 | C564: 45428 | D564: CUST-8622 | E564: =PROPER(TRIM([1]raw_orders!E564)) -> Karan Malhotra | F564: =PROPER(TRIM([1]raw_orders!F564)) -> Consumer | G564: =IF('[1]Cleaned Text Field'!G564="","Unknown",'[1]Cleaned Text Field'!G564) -> North | H564: =PROPER(TRIM([1]raw_orders!H564)) -> Punjab | I564: =PROPER(TRIM([1]raw_orders!I564)) -> Ludhiana | J564: =PROPER(TRIM([1]raw_orders!J564)) -> Office Supplies | K564: =PROPER(TRIM([1]raw_orders!K564)) -> Binders | L564: Elite Binders 143 | M564: =IF('[1]Cleaned Text Field'!M564="","Unknown",'[1]Cleaned Text Field'!M564) -> Same Day | N564: =IF('[1]Cleaned Text Field'!N564="",0,'[1]Cleaned Text Field'!N564) -> 7 | O564: 121.54 | P564: =IF('[1]Cleaned Text Field'!P564="",0,'[1]Cleaned Text Field'!P564) -> 0.2 | Q564: 680.62 | R564: 463.49 | S564: 217.13 | T564: =PROPER(TRIM([1]raw_orders!T564)) -> Failed | U564: =PROPER(TRIM([1]raw_orders!U564)) -> Returned | V564: =IF(Q564=0,0,S564/Q564) -> 0.31901795 | W564: =TEXT(B564,"mmmm") -> May | X564: =YEAR(B564) -> 2024 | Y564: =C564-B564 -> 6 | Z564: =P564 -> 0.2 | AA564: =N564*O564*(1-P564) -> 680.624 | AB564: =Q564-R564 -> 217.13 | AC564: =IF(OR(B564="",C564="",AA564<=0),"Invalid",IF(Y564<0,"Warning",IF(Z564>100%,"Warning","Clean"))) -> Clean
A565: ORD-2024-10564 | B565: 45418 | C565: 45631 | D565: CUST-8776 | E565: =PROPER(TRIM([1]raw_orders!E565)) -> Arjun Bose | F565: =PROPER(TRIM([1]raw_orders!F565)) -> Corporate | G565: =IF('[1]Cleaned Text Field'!G565="","Unknown",'[1]Cleaned Text Field'!G565) -> West | H565: =PROPER(TRIM([1]raw_orders!H565)) -> Goa | I565: =PROPER(TRIM([1]raw_orders!I565)) -> Panaji | J565: =PROPER(TRIM([1]raw_orders!J565)) -> Furniture | K565: =PROPER(TRIM([1]raw_orders!K565)) -> Tables | L565: Classic Tables 560 | M565: =IF('[1]Cleaned Text Field'!M565="","Unknown",'[1]Cleaned Text Field'!M565) -> Standard Class | N565: =IF('[1]Cleaned Text Field'!N565="",0,'[1]Cleaned Text Field'!N565) -> 9 | O565: 790.97 | P565: =IF('[1]Cleaned Text Field'!P565="",0,'[1]Cleaned Text Field'!P565) -> 0.2 | Q565: 5694.98 | R565: 4618.33 | S565: 1076.65 | T565: =PROPER(TRIM([1]raw_orders!T565)) -> Pending | U565: =PROPER(TRIM([1]raw_orders!U565)) -> Cancelled | V565: =IF(Q565=0,0,S565/Q565) -> 0.18905246 | W565: =TEXT(B565,"mmmm") -> May | X565: =YEAR(B565) -> 2024 | Y565: =C565-B565 -> 213 | Z565: =P565 -> 0.2 | AA565: =N565*O565*(1-P565) -> 5694.984 | AB565: =Q565-R565 -> 1076.65 | AC565: =IF(OR(B565="",C565="",AA565<=0),"Invalid",IF(Y565<0,"Warning",IF(Z565>100%,"Warning","Clean"))) -> Clean
A566: ORD-2024-10565 | B566: 45606 | C566: 45610 | D566: CUST-9100 | E566: =PROPER(TRIM([1]raw_orders!E566)) -> Sneha Kapoor | F566: =PROPER(TRIM([1]raw_orders!F566)) -> Corporate | G566: =IF('[1]Cleaned Text Field'!G566="","Unknown",'[1]Cleaned Text Field'!G566) -> South | H566: =PROPER(TRIM([1]raw_orders!H566)) -> Andhra Pradesh | I566: =PROPER(TRIM([1]raw_orders!I566)) -> Vijayawada | J566: =PROPER(TRIM([1]raw_orders!J566)) -> Furniture | K566: =PROPER(TRIM([1]raw_orders!K566)) -> Tables | L566: Basic Tables 759 | M566: =IF('[1]Cleaned Text Field'!M566="","Unknown",'[1]Cleaned Text Field'!M566) -> First Class | N566: =IF('[1]Cleaned Text Field'!N566="",0,'[1]Cleaned Text Field'!N566) -> 2 | O566: 921.34 | P566: =IF('[1]Cleaned Text Field'!P566="",0,'[1]Cleaned Text Field'!P566) -> 0.2 | Q566: 1474.14 | R566: 968.46 | S566: 505.68 | T566: =PROPER(TRIM([1]raw_orders!T566)) -> Paid | U566: =PROPER(TRIM([1]raw_orders!U566)) -> Completed | V566: =IF(Q566=0,0,S566/Q566) -> 0.3430339 | W566: =TEXT(B566,"mmmm") -> November | X566: =YEAR(B566) -> 2024 | Y566: =C566-B566 -> 4 | Z566: =P566 -> 0.2 | AA566: =N566*O566*(1-P566) -> 1474.144 | AB566: =Q566-R566 -> 505.68 | AC566: =IF(OR(B566="",C566="",AA566<=0),"Invalid",IF(Y566<0,"Warning",IF(Z566>100%,"Warning","Clean"))) -> Clean
... A606: ORD-2025-10605 | B606: 45779 | C606: 45694 | D606: CUST-4526 | E606: =PROPER(TRIM([1]raw_orders!E606)) -> Ananya Rao | F606: =PROPER(TRIM([1]raw_orders!F606)) -> Consumer | G606: =IF('[1]Cleaned Text Field'!G606="","Unknown",'[1]Cleaned Text Field'!G606) -> West | H606: =PROPER(TRIM([1]raw_orders!H606)) -> Madhya Pradesh | I606: =PROPER(TRIM([1]raw_orders!I606)) -> Indore | J606: =PROPER(TRIM([1]raw_orders!J606)) -> Office Supplies | K606: =PROPER(TRIM([1]raw_orders!K606)) -> Binders | L606: Max Binders 547 | M606: =IF('[1]Cleaned Text Field'!M606="","Unknown",'[1]Cleaned Text Field'!M606) -> Same Day | N606: =IF('[1]Cleaned Text Field'!N606="",0,'[1]Cleaned Text Field'!N606) -> 3 | O606: 1076.3 | P606: =IF('[1]Cleaned Text Field'!P606="",0,'[1]Cleaned Text Field'!P606) -> 0 | Q606: 3228.9 | R606: 1853.23 | S606: 1375.67 | T606: =PROPER(TRIM([1]raw_orders!T606)) -> Paid | U606: =PROPER(TRIM([1]raw_orders!U606)) -> Completed | V606: =IF(Q606=0,0,S606/Q606) -> 0.42604912 | W606: =TEXT(B606,"mmmm") -> May | X606: =YEAR(B606) -> 2025 | Y606: =C606-B606 -> -85 | Z606: =P606 -> 0 | AA606: =N606*O606*(1-P606) -> 3228.9 | AB606: =Q606-R606 -> 1375.67 | AC606: =IF(OR(B606="",C606="",AA606<=0),"Invalid",IF(Y606<0,"Warning",IF(Z606>100%,"Warning","Clean"))) -> Warning
A607: ORD-2025-10606 | B607: 45847 | C607: 45851 | D607: CUST-4447 | E607: =PROPER(TRIM([1]raw_orders!E607)) -> Kabir Singh | F607: =PROPER(TRIM([1]raw_orders!F607)) -> Corporate | G607: =IF('[1]Cleaned Text Field'!G607="","Unknown",'[1]Cleaned Text Field'!G607) -> West | H607: =PROPER(TRIM([1]raw_orders!H607)) -> Goa | I607: =PROPER(TRIM([1]raw_orders!I607)) -> Panaji | J607: =PROPER(TRIM([1]raw_orders!J607)) -> Furniture | K607: =PROPER(TRIM([1]raw_orders!K607)) -> Furnishings | L607: Pro Furnishings 267 | M607: =IF('[1]Cleaned Text Field'!M607="","Unknown",'[1]Cleaned Text Field'!M607) -> Second Class | N607: =IF('[1]Cleaned Text Field'!N607="",0,'[1]Cleaned Text Field'!N607) -> 5 | O607: 1680.01 | P607: =IF('[1]Cleaned Text Field'!P607="",0,'[1]Cleaned Text Field'!P607) -> 85% | Q607: 7560.04 | R607: 6448.05 | S607: 1111.99 | T607: =PROPER(TRIM([1]raw_orders!T607)) -> Paid | U607: =PROPER(TRIM([1]raw_orders!U607)) -> Cancelled | V607: =IF(Q607=0,0,S607/Q607) -> 0.14708785 | W607: =TEXT(B607,"mmmm") -> July | X607: =YEAR(B607) -> 2025 | Y607: =C607-B607 -> 4 | Z607: =VALUE(SUBSTITUTE(P607,"%",""))/100 -> 0.85 | AA607: =N607*O607*(1-P607) -> 1260.0075 | AB607: =Q607-R607 -> 1111.99 | AC607: =IF(OR(B607="",C607="",AA607<=0),"Invalid",IF(Y607<0,"Warning",IF(Z607>100%,"Warning","Clean"))) -> Clean
A608: ORD-2025-10607 | B608: 45710 | C608: 45716 | D608: CUST-2698 | E608: =PROPER(TRIM([1]raw_orders!E608)) -> Rahul Verma | F608: =PROPER(TRIM([1]raw_orders!F608)) -> Home Office | G608: =IF('[1]Cleaned Text Field'!G608="","Unknown",'[1]Cleaned Text Field'!G608) -> West | H608: =PROPER(TRIM([1]raw_orders!H608)) -> Madhya Pradesh | I608: =PROPER(TRIM([1]raw_orders!I608)) -> Indore | J608: =PROPER(TRIM([1]raw_orders!J608)) -> Technology | K608: =PROPER(TRIM([1]raw_orders!K608)) -> Copiers | L608: Max Copiers 520 | M608: =IF('[1]Cleaned Text Field'!M608="","Unknown",'[1]Cleaned Text Field'!M608) -> Same Day | N608: =IF('[1]Cleaned Text Field'!N608="",0,'[1]Cleaned Text Field'!N608) -> 3 | O608: 3890.81 | P608: =IF('[1]Cleaned Text Field'!P608="",0,'[1]Cleaned Text Field'!P608) -> 0.25 | Q608: 8754.32 | R608: 6238.9 | S608: 2515.42 | T608: =PROPER(TRIM([1]raw_orders!T608)) -> Paid | U608: =PROPER(TRIM([1]raw_orders!U608)) -> Completed | V608: =IF(Q608=0,0,S608/Q608) -> 0.28733471 | W608: =TEXT(B608,"mmmm") -> February | X608: =YEAR(B608) -> 2025 | Y608: =C608-B608 -> 6 | Z608: =P608 -> 0.25 | AA608: =N608*O608*(1-P608) -> 8754.3225 | AB608: =Q608-R608 -> 2515.42 | AC608: =IF(OR(B608="",C608="",AA608<=0),"Invalid",IF(Y608<0,"Warning",IF(Z608>100%,"Warning","Clean"))) -> Clean
...

Sheet Missing_Value_Summary
A1: Field | B1: Missing Count | C1: Action Taken
A2: order_id | B2: =COUNTIF(A2:A1000,"Unknown") -> 0
A3: order_date | B3: 0
A4: ship_date | B4: 0
A5: customer_id | B5: 0
A6: customer_name | B6: 0
A7: segment | B7: 0
A8: region | B8: =COUNTIF(data!G2:G933,"Unknown") -> 26 | C8: Filled with Unknown
A9: state | B9: 0
A10: city | B10: 0
A11: category | B11: 0
A12: sub_category | B12: 0
A13: product_name | B13: 0
A14: ship_mode | B14: =COUNTIF(data!M2:M933,"Unknown") -> 22 | C14: Filled with Unknown
A15: quantity | B15: 0
A16: unit_price | B16: 0
A17: discount | B17: =COUNTIF(data!P2:P933,0) -> 263 | C17: Filled with 0.00 if valid
A18: sales | B18: 0
A19: cost | B19: 0
A20: profit | B20: 0
A21: payment_status | B21: 0
A22: order_status | B22: 0
A23: Profit Margin | B23: 0
A24: Order moth | B24: 0
A25: Order Year | B25: 0
A26: Shipping_Delay_Days | B26: 0
A27: Cleaned Discount | B27: =COUNTIF(data!Z2:Z933,0%) -> 263 | C27: Filled with 0 if valid
A28: Calculated Sales | B28: 0
A29: Calculated Profit | B29: 0
A30: Data Quality Flag | B30: 0

Sheet Duplicate_Summary
A1: Metric | B1: Value
A2: Exact duplicate rows | B2: 20
A3: Duplicate order IDs | B3: 31
A4: Records removed | B4: 20
A5: Records flagged | B5: 31
A6: Logic | B6: Exact duplicates removed; conflicting IDs flagged.

Sheet Invalid_Discount_Summary
A1: Metric | B1: Count
A2: Missing | B2: =COUNTIF(data!Z2:Z933,0%) -> 263
A3: Negative | B3: =COUNTIF(data!Z2:'data'!Z933,"<0%") -> 16
A4: > Allowed Range | B4: =COUNTIF(data!Z3:'data'!Z934,">0%") -> 652
A5: Total Invalid | B5: 16

Sheet Sales_Profit_Calculation_Mismat
A1: Metric | B1: Count
A2: Sales Mismatch | B2: =COUNTIFS(data!Q2:Q933,data!AA2:AA933) -> 1
A3: Profit Mismatch | B3: =COUNTIFS(data!S2:S933,data!AB2:AB933) -> 1

Sheet Final_Clean_vs_Flagged
A1: Metric | B1: Count
A2: Total | B2: 932
A3: Clean | B3: =COUNTIF(data!AC2:AC933,"Clean") -> 838
A4: Warning | B4: =COUNTIF(data!AC2:AC933,"Warning") -> 94
A5: Invalid | B5: =COUNTIF(data!AC2:AC933,"Invalid") -> 0
